Workbook

Sheet 00_Inicio
A1: AG LEGAL | Sistema financiero y comercial 2026
A2: Modelo reconstruido a partir del detalle mensual. Separa cobrado, cartera en ejecución y presupuesto julio-diciembre.
A4: Regla | B4: Aplicación
A5: Código | B5: AGL-Categoría-Subcategoría-000
A6: Clasificación | B6: Cada servicio tiene una categoría financiera principal y múltiples etiquetas.
A7: Duplicados | B7: No se duplica el mismo servicio; se relaciona mediante etiquetas y servicios vinculados.
A8: Ingreso | B8: Solo dinero efectivamente cobrado.
A9: Cartera | B9: Trabajo contratado o ganado que requiere finalizarse antes del cobro.
A10: Proyección | B10: Cobro esperado por mes, ajustado por probabilidad.
A11: Corrección David Juárez | B11: Honorarios $1,500; adelanto cobrado $200; saldo pendiente $1,300.
A14: Hoja | B14: Uso principal | C14: Usuario | D14: Carácter
A15: 12_Reglas_Comision | B15: Reglas de salario variable de Andrea | C15: Administración / desarrollador | D15: Normativo
A16: 13_Especificacion_Sistema | B16: Modelo de datos y reglas de implementación | C16: Desarrollador | D16: Crítico
A17: 14_Dashboard_KPIs | B17: Indicadores y visuales requeridos | C17: Desarrollador / socios | D17: Crítico
A18: 15_Cumplimiento_Metas | B18: Estructura de seguimiento meta vs real | C18: Sistema / administración | D18: Operativo
A19: 03_Catalogo_Servicios | B19: Maestro de códigos a importar | C19: Desarrollador | D19: Crítico
A21: Hoja | B21: Contenido | C21: Uso | D21: Importancia
A22: 04_Plan_Cuentas | B22: Códigos oficiales de ingresos y egresos | C22: Importar al sistema | D22: Crítica
A23: 15_Cumplimiento_Metas | B23: Meta y realidad por familia/mes | C23: Control temporal y sistema | D23: Crítica
A24: 16_Movimientos_Codificados | B24: Estructura de cada movimiento financiero | C24: Desarrollo e importación | D24: Crítica
A25: 17_Resumen_Mensual | B25: Meta, utilidad mínima y cumplimiento consolidado | C25: Dashboard y socios | D25: Crítica
A27: Hoja | B27: Contenido | C27: Responsable principal | D27: Uso
... A34: PEN | B34: Derecho Penal creado como categoría independiente | C34: Catálogo y sistema | D34: Crítica
A36: HOJA PRINCIPAL PARA ENVIAR AL DESARROLLADOR
A37: Hoja | B37: Qué contiene | C37: Acción | D37: Prioridad
A38: 00_PARA_DESARROLLADOR | B38: Resumen único de arquitectura, campos, relaciones, dashboard y fuentes maestras | C38: Leer primero | D38: Crítica
A39: 13_Especificacion_Sistema | B39: Anexo técnico ampliado | C39: Consultar después | D39: Alta

Sheet 01_Categorias
A1: 01 | Categorías maestras
A2: Las categorías representan líneas jurídicas o comerciales independientes. Los códigos son permanentes y no reutilizables.
A4: Código | B4: Categoría | C4: Descripción | D4: Estado
A5: NOT | B5: Servicios Notariales | C5: Actos y diligencias formalizados mediante función notarial. | D5: Activo
A6: LIT | B6: Litigios y Controversias | C6: Representación judicial y solución de controversias. | D6: Activo
A7: PEN | B7: Derecho Penal | C7: Defensa penal, representación de víctimas, actuación ante FGR y tribunales, delitos económicos y ejecución penal. | D7: Activo
A8: FAM | B8: Derecho de Familia | C8: Procesos familiares, filiación, alimentos y autoridad parental. | D8: Activo
A9: COR | B9: Corporativo y Empresarial | C9: Sociedades, gobierno corporativo y asesoría empresarial. | D9: Activo
A10: RAI | B10: Bienes Raíces e Inversiones | C10: Operaciones inmobiliarias, registrales, catastrales y de inversión. | D10: Activo
A11: ADM | B11: Derecho Administrativo | C11: Procedimientos y trámites ante instituciones públicas. | D11: Activo
A12: MIG | B12: Migración y Extranjería | C12: Residencias, naturalización, NIT y regularización migratoria. | D12: Activo
A13: REL | B13: Relocalización | C13: Acompañamiento integral para establecerse o invertir en El Salvador. | D13: Activo
A14: LAB | B14: Laboral Preventivo | C14: Contratos, reglamentos, terminaciones e inspecciones laborales. | D14: Activo
A15: IPI | B15: Propiedad Intelectual | C15: Marcas, derechos de autor, patentes y diseños. | D15: Activo
... A20: CTR | B20: Contratos y Obligaciones | C20: Redacción, revisión y negociación contractual. | D20: Activo

Sheet 02_Subcategorias
A1: 02 | Subcategorías maestras
A2: Cada subcategoría pertenece a una categoría activa y utiliza un código único de tres letras distinto del código de su categoría.
A4: Código categoría | B4: Categoría | C4: Código subcategoría | D4: Subcategoría | E4: Código compuesto | F4: Estado
A5: NOT | B5: Servicios Notariales | C5: EST | D5: Escrituras sobre inmuebles | E5: NOT-EST | F5: Activo
A6: NOT | B6: Servicios Notariales | C6: VEH | D6: Instrumentos sobre vehículos | E6: NOT-VEH | F6: Activo
A7: NOT | B7: Servicios Notariales | C7: EFA | D7: Estado familiar | E7: NOT-EFA | F7: Activo
A8: NOT | B8: Servicios Notariales | C8: PAT | D8: Patrimonial notarial | E8: NOT-PAT | F8: Activo
A9: NOT | B9: Servicios Notariales | C9: OBL | D9: Obligaciones notariales | E9: NOT-OBL | F9: Activo
A10: NOT | B10: Servicios Notariales | C10: POD | D10: Poderes | E10: NOT-POD | F10: Activo
A11: NOT | B11: Servicios Notariales | C11: AUC | D11: Auténticas y certificaciones | E11: NOT-AUC | F11: Activo
A12: NOT | B12: Servicios Notariales | C12: DIL | D12: Diligencias notariales | E12: NOT-DIL | F12: Activo
A13: LIT | B13: Litigios y Controversias | C13: MER | D13: Mercantil | E13: LIT-MER | F13: Activo
A14: LIT | B14: Litigios y Controversias | C14: CIV | D14: Civil | E14: LIT-CIV | F14: Activo
A15: LIT | B15: Litigios y Controversias | C15: TRL | D15: Laboral contencioso | E15: LIT-TRL | F15: Activo
... A83: PEN | B83: Derecho Penal | C83: PJV | D83: Justicia penal juvenil | E83: PEN-PJV | F83: Activo

Sheet 03_Catalogo_Servicios
A1: 03 | Catálogo maestro de servicios
A2: Derecho Penal se administra como categoría independiente. Los códigos existentes de otras áreas se conservan para proteger el histórico.
A4: Código servicio | B4: Cod. categoría | C4: Categoría | D4: Cod. subcategoría | E4: Subcategoría | F4: Servicio | G4: Etiquetas | H4: Estado | I4: Unidad de cobro | J4: Responsable | K4: Tarifa referencia ($) | L4: Costo directo referencia ($) | M4: Horas estándar | N4: Margen referencia ($)
A5: AGL-NOT-EST-001 | B5: NOT | C5: Servicios Notariales | D5: EST | E5: Escrituras sobre inmuebles | F5: Escritura de compraventa de inmueble | G5: escritura,inmueble,CNR | H5: Activo | I5: Por definir | J5: Por definir | K5: 0 | L5: 0 | M5: 0 | N5: =K5-L5 -> 0
A6: AGL-NOT-EST-002 | B6: NOT | C6: Servicios Notariales | D6: EST | E6: Escrituras sobre inmuebles | F6: Promesa de compraventa de inmueble | G6: escritura,inmueble,CNR | H6: Activo | I6: Por definir | J6: Por definir | K6: 0 | L6: 0 | M6: 0 | N6: =K6-L6 -> 0
A7: AGL-NOT-EST-003 | B7: NOT | C7: Servicios Notariales | D7: EST | E7: Escrituras sobre inmuebles | F7: Escritura de donación de inmueble | G7: escritura,inmueble,CNR | H7: Activo | I7: Por definir | J7: Por definir | K7: 0 | L7: 0 | M7: 0 | N7: =K7-L7 -> 0
A8: AGL-NOT-EST-004 | B8: NOT | C8: Servicios Notariales | D8: EST | E8: Escrituras sobre inmuebles | F8: Cancelación notarial de hipoteca | G8: escritura,inmueble,CNR | H8: Activo | I8: Por definir | J8: Por definir | K8: 0 | L8: 0 | M8: 0 | N8: =K8-L8 -> 0
A9: AGL-NOT-VEH-001 | B9: NOT | C9: Servicios Notariales | D9: VEH | E9: Instrumentos sobre vehículos | F9: Compraventa de vehículo | G9: vehículo,tránsito | H9: Activo | I9: Por definir | J9: Por definir | K9: 0 | L9: 0 | M9: 0 | N9: =K9-L9 -> 0
A10: AGL-NOT-VEH-002 | B10: NOT | C10: Servicios Notariales | D10: VEH | E10: Instrumentos sobre vehículos | F10: Arrendamiento de vehículo | G10: vehículo,tránsito | H10: Activo | I10: Por definir | J10: Por definir | K10: 0 | L10: 0 | M10: 0 | N10: =K10-L10 -> 0
A11: AGL-NOT-VEH-003 | B11: NOT | C11: Servicios Notariales | D11: VEH | E11: Instrumentos sobre vehículos | F11: Autorización de salida de vehículo | G11: vehículo,tránsito | H11: Activo | I11: Por definir | J11: Por definir | K11: 0 | L11: 0 | M11: 0 | N11: =K11-L11 -> 0
A12: AGL-NOT-EFA-001 | B12: NOT | C12: Servicios Notariales | D12: EFA | E12: Estado familiar | F12: Matrimonio civil | G12: familia,matrimonio,menor | H12: Activo | I12: Por definir | J12: Por definir | K12: 0 | L12: 0 | M12: 0 | N12: =K12-L12 -> 0
A13: AGL-NOT-EFA-002 | B13: NOT | C13: Servicios Notariales | D13: EFA | E13: Estado familiar | F13: Reconocimiento voluntario de hijo | G13: familia,matrimonio,menor | H13: Activo | I13: Por definir | J13: Por definir | K13: 0 | L13: 0 | M13: 0 | N13: =K13-L13 -> 0
A14: AGL-NOT-EFA-003 | B14: NOT | C14: Servicios Notariales | D14: EFA | E14: Estado familiar | F14: Permiso de salida de menor | G14: familia,matrimonio,menor | H14: Activo | I14: Por definir | J14: Por definir | K14: 0 | L14: 0 | M14: 0 | N14: =K14-L14 -> 0
A15: AGL-NOT-EFA-004 | B15: NOT | C15: Servicios Notariales | D15: EFA | E15: Estado familiar | F15: Autorización para pasaporte de menor | G15: familia,matrimonio,menor | H15: Activo | I15: Por definir | J15: Por definir | K15: 0 | L15: 0 | M15: 0 | N15: =K15-L15 -> 0
A16: AGL-NOT-EFA-005 | B16: NOT | C16: Servicios Notariales | D16: EFA | E16: Estado familiar | F16: Acta notarial relacionada con familia | G16: familia,matrimonio,menor | H16: Activo | I16: Por definir | J16: Por definir | K16: 0 | L16: 0 | M16: 0 | N16: =K16-L16 -> 0
... A209: AGL-PEN-PJV-002 | B209: PEN | C209: Derecho Penal | D209: PJV | E209: Justicia penal juvenil | F209: Representación de víctima en proceso penal juvenil | G209: penal juvenil,victima | H209: Activo | I209: Por definir | J209: Por definir | K209: 0 | L209: 0 | M209: 0 | N209: =K209-L209 -> 0

Sheet 04_Registro_Operaciones
A1: 04 | Registro histórico de operaciones
A2: Registro reconstruido de marzo a julio. Ingreso significa cobrado; egreso significa pagado.
A4: Fecha | B4: Mes | C4: Cliente | D4: Concepto original | E4: Tipo | F4: Monto ($) | G4: Estado | H4: Código servicio | I4: Servicio normalizado | J4: Notas
A5: 46082 | B5: Marzo | C5: Lic. Palma | D5: Escritura de compraventa | E5: Ingreso | F5: 250 | G5: Cobrado | H5: AGL-NOT-INM-001 | I5: Escritura de compraventa de inmueble
A6: 46082 | B6: Marzo | C6: Varios | D6: Certificación de documentos | E6: Ingreso | F6: 96 | G6: Cobrado | H6: AGL-NOT-AUT-002 | I6: Certificación de documentos
A7: 46082 | B7: Marzo | C7: Emiliano | D7: Asesoría legal | E7: Ingreso | F7: 50 | G7: Cobrado | H7: AGL-ADM-REG-001 | I7: Gestión ante institución pública
A8: 46082 | B8: Marzo | C8: Andre Pranckevicius | D8: Elaboración de escrito | E8: Ingreso | F8: 50 | G8: Cobrado | H8: AGL-ADM-REG-001 | I8: Gestión ante institución pública
A9: 46092 | B9: Marzo | C9: Santos Alonso Canales | D9: Acompañamiento administrativo | E9: Ingreso | F9: 50 | G9: Cobrado | H9: AGL-ADM-REG-002 | I9: Acompañamiento administrativo
A10: 46094 | B10: Marzo | C10: Lic. Palma | D10: Alquiler de instalaciones | E10: Ingreso | F10: 80 | G10: Cobrado
A11: 46095 | B11: Marzo | C11: Douglas | D11: Alquiler de instalaciones | E11: Ingreso | F11: 10 | G11: Cobrado
A12: 46098 | B12: Marzo | C12: Patricia de Hernández | D12: Poder, asesoría y conciliación | E12: Ingreso | F12: 200 | G12: Cobrado | H12: AGL-NOT-POD-003 | I12: Poder especial
A13: 46098 | B13: Marzo | C13: Lucio Orellana | D13: Poder judicial | E13: Ingreso | F13: 50 | G13: Cobrado | H13: AGL-NOT-POD-001 | I13: Poder general judicial
A14: 46098 | B14: Marzo | C14: Yoni Estuardo | D14: Acompañamientos a Migración | E14: Ingreso | F14: 45 | G14: Cobrado | H14: AGL-MIG-PER-002 | I14: Acompañamiento a Migración
A15: 46099 | B15: Marzo | C15: PGR | D15: Acta notarial deuda alimenticia | E15: Ingreso | F15: 10 | G15: Cobrado | H15: AGL-NOT-AUT-004 | I15: Acta notarial
A16: 46100 | B16: Marzo | C16: ISSS | D16: Acta notarial | E16: Ingreso | F16: 10 | G16: Cobrado | H16: AGL-NOT-AUT-004 | I16: Acta notarial
A17: 46101 | B17: Marzo | C17: José Antonio Mineros | D17: Asesoría legal | E17: Ingreso | F17: 30 | G17: Cobrado | H17: AGL-ADM-REG-001 | I17: Gestión ante institución pública
A18: 46101 | B18: Marzo | C18: José Antonio Mineros | D18: Negociación de deuda BAC | E18: Ingreso | F18: 30 | G18: Cobrado | H18: AGL-LIT-ADR-001 | I18: Negociación extrajudicial
A19: 46102 | B19: Marzo | C19: Karla Muñoz | D19: Cesión de derechos hereditarios | E19: Ingreso | F19: 50 | G19: Cobrado | H19: AGL-NOT-PAT-003 | I19: Cesión de derechos hereditarios
A20: 46102 | B20: Marzo | C20: Karla Muñoz | D20: Aceptación de herencia | E20: Ingreso | F20: 50 | G20: Cobrado | H20: AGL-NOT-PAT-002 | I20: Aceptación de herencia notarial
A21: 46105 | B21: Marzo | C21: Ana Jovel | D21: Visita a municipalidad | E21: Ingreso | F21: 30 | G21: Cobrado | H21: AGL-ADM-MUN-001 | I21: Trámite ante Alcaldía
A22: 46105 | B22: Marzo | C22: Samuel Padillas | D22: Cancelación de hipoteca | E22: Ingreso | F22: 50 | G22: Cobrado | H22: AGL-NOT-INM-004 | I22: Cancelación notarial de hipoteca
A23: 46112 | B23: Marzo | D23: Reparaciones e insumos | E23: Egreso | F23: 16.2 | G23: Pagado | J23: Resumen reconstruido del archivo fuente
A24: 46112 | B24: Marzo | D24: Viáticos CNR | E24: Egreso | F24: 10 | G24: Pagado | J24: Resumen reconstruido del archivo fuente
A25: 46112 | B25: Marzo | D25: Servicios notariales terceros | E25: Egreso | F25: 150 | G25: Pagado | J25: Resumen reconstruido del archivo fuente
A26: 46112 | B26: Marzo | D26: Renta | E26: Egreso | F26: 400 | G26: Pagado | J26: Resumen reconstruido del archivo fuente
A27: 46112 | B27: Marzo | D27: Sueldo | E27: Egreso | F27: 250 | G27: Pagado | J27: Resumen reconstruido del archivo fuente
A28: 46118 | B28: Abril | C28: Marcela Vaquero | D28: Autorización salida de vehículo | E28: Ingreso | F28: 25 | G28: Cobrado | H28: AGL-NOT-VEH-003 | I28: Autorización de salida de vehículo
A29: 46119 | B29: Abril | C29: Varios | D29: Compraventa de vehículo | E29: Ingreso | F29: 25 | G29: Cobrado | H29: AGL-NOT-VEH-001 | I29: Compraventa de vehículo
A30: 46120 | B30: Abril | C30: David Juárez | D30: Investigación sobre herencia | E30: Ingreso | F30: 30 | G30: Cobrado | H30: AGL-INM-REG-001 | I30: Investigación registral
A31: 46127 | B31: Abril | C31: Ana María Linares | D31: Donaciones | E31: Ingreso | F31: 204 | G31: Cobrado | H31: AGL-NOT-INM-003 | I31: Escritura de donación de inmueble
A32: 46134 | B32: Abril | C32: Marvin Villalta | D32: Contratos de arrendamiento | E32: Ingreso | F32: 90 | G32: Cobrado | H32: AGL-INM-ARR-001 | I32: Contrato de arrendamiento residencial
A33: 46136 | B33: Abril | C33: Inversiones ZR | D33: Compraventa de vehículos | E33: Ingreso | F33: 50 | G33: Cobrado | H33: AGL-NOT-VEH-001 | I33: Compraventa de vehículo
A34: 46136 | B34: Abril | C34: Inversiones ZR | D34: Reimpresión compraventa vehículo | E34: Ingreso | F34: 10 | G34: Cobrado | H34: AGL-NOT-VEH-001 | I34: Compraventa de vehículo
A35: 46136 | B35: Abril | C35: Douglas | D35: Alquiler de instalaciones | E35: Ingreso | F35: 10 | G35: Cobrado
A36: 46137 | B36: Abril | C36: Margarita Vaquerano | D36: Asesoría | E36: Ingreso | F36: 30 | G36: Cobrado | H36: AGL-ADM-REG-001 | I36: Gestión ante institución pública
A37: 46142 | B37: Abril | D37: Certificaciones y tasas | E37: Egreso | F37: 26.36 | G37: Pagado | J37: Resumen reconstruido del archivo fuente
A38: 46142 | B38: Abril | D38: Capacitación | E38: Egreso | F38: 75 | G38: Pagado | J38: Resumen reconstruido del archivo fuente
A39: 46142 | B39: Abril | D39: Energía eléctrica | E39: Egreso | F39: 11.14 | G39: Pagado | J39: Resumen reconstruido del archivo fuente
A40: 46142 | B40: Abril | D40: Renta | E40: Egreso | F40: 400 | G40: Pagado | J40: Resumen reconstruido del archivo fuente
A41: 46142 | B41: Abril | D41: Sueldo | E41: Egreso | F41: 450 | G41: Pagado | J41: Resumen reconstruido del archivo fuente
A42: 46146 | B42: Mayo | C42: Varios | D42: Copias | E42: Ingreso | F42: 5.5 | G42: Cobrado | H42: AGL-NOT-AUT-002 | I42: Certificación de documentos
A43: 46146 | B43: Mayo | C43: Varios | D43: Asistencia legal en PNC + asesoría | E43: Ingreso | F43: 100 | G43: Cobrado | H43: AGL-ADM-REG-002 | I43: Acompañamiento administrativo
A44: 46147 | B44: Mayo | C44: ISSS | D44: Actas notariales | E44: Ingreso | F44: 40 | G44: Cobrado | H44: AGL-NOT-AUT-004 | I44: Acta notarial
A45: 46151 | B45: Mayo | C45: Margarita Vaquerano | D45: Contrato, escritos OPAMSS y certificaciones | E45: Ingreso | F45: 75 | G45: Cobrado | H45: AGL-ADM-OPM-001 | I45: Trámite o escrito ante OPAMSS
A46: 46152 | B46: Mayo | C46: Andre Pranckevicius | D46: Gestiones | E46: Ingreso | F46: 100 | G46: Cobrado | H46: AGL-ADM-REG-001 | I46: Gestión ante institución pública
A47: 46152 | B47: Mayo | C47: Karolina Ranzinka | D47: Asesorías | E47: Ingreso | F47: 50 | G47: Cobrado | H47: AGL-ADM-REG-001 | I47: Gestión ante institución pública
A48: 46152 | B48: Mayo | C48: Christine Miranda | D48: Gestiones Banco Hipotecario | E48: Ingreso | F48: 450 | G48: Cobrado | H48: AGL-ADM-REG-001 | I48: Gestión ante institución pública
A49: 46154 | B49: Mayo | C49: Hugo Gallegos | D49: Contrato de regencia | E49: Ingreso | F49: 25 | G49: Cobrado | H49: AGL-CON-CIV-001 | I49: Contrato de prestación de servicios
A50: 46156 | B50: Mayo | C50: Lic. Palma | D50: Compraventa | E50: Ingreso | F50: 150 | G50: Cobrado | H50: AGL-NOT-INM-001 | I50: Escritura de compraventa de inmueble
A51: 46156 | B51: Mayo | C51: Lidia de García | D51: Cancelación de hipoteca | E51: Ingreso | F51: 50 | G51: Cobrado | H51: AGL-NOT-INM-004 | I51: Cancelación notarial de hipoteca
A52: 46159 | B52: Mayo | C52: Douglas Rodríguez | D52: Poder | E52: Ingreso | F52: 35 | G52: Cobrado | H52: AGL-NOT-POD-003 | I52: Poder especial
A53: 46159 | B53: Mayo | C53: René Vaquero | D53: Autorización | E53: Ingreso | F53: 40 | G53: Cobrado | H53: AGL-NOT-AUT-004 | I53: Acta notarial
... A62: 46173 | B62: Mayo | C62: Alfredo Villalobos | D62: Asesoría | E62: Ingreso | F62: 30 | G62: Cobrado | H62: AGL-ADM-REG-001 | I62: Gestión ante institución pública
A63: 46173 | B63: Mayo | D63: Agua, papel y energía | E63: Egreso | F63: 26.46 | G63: Pagado | J63: Resumen reconstruido del archivo fuente
A64: 46173 | B64: Mayo | D64: Certificaciones y publicaciones | E64: Egreso | F64: 50.5 | G64: Pagado | J64: Resumen reconstruido del archivo fuente
A65: 46173 | B65: Mayo | D65: Renta | E65: Egreso | F65: 400 | G65: Pagado | J65: Resumen reconstruido del archivo fuente
A66: 46173 | B66: Mayo | D66: Salario | E66: Egreso | F66: 450 | G66: Pagado | J66: Resumen reconstruido del archivo fuente
A67: 46173 | B67: Mayo | D67: Capacitación | E67: Egreso | F67: 60 | G67: Pagado | J67: Resumen reconstruido del archivo fuente
A68: 46173 | B68: Mayo | D68: Mantenimiento | E68: Egreso | F68: 35 | G68: Pagado | J68: Resumen reconstruido del archivo fuente
A69: 46181 | B69: Junio | C69: SIAGRO | D69: Certificaciones y auténticas | E69: Ingreso | F69: 25 | G69: Cobrado | H69: AGL-NOT-AUT-001 | I69: Auténtica de firma
A70: 46182 | B70: Junio | C70: Marvin Villalta | D70: Declaración jurada | E70: Ingreso | F70: 25 | G70: Cobrado | H70: AGL-NOT-AUT-003 | I70: Declaración jurada
A71: 46186 | B71: Junio | C71: Andre | D71: Poder | E71: Ingreso | F71: 100 | G71: Cobrado | H71: AGL-NOT-POD-003 | I71: Poder especial
A72: 46186 | B72: Junio | C72: René Vaquero | D72: Compraventa | E72: Ingreso | F72: 25 | G72: Cobrado | H72: AGL-NOT-VEH-001 | I72: Compraventa de vehículo
A73: 46186 | B73: Junio | C73: Lic. Palma | D73: Protocolización de estatutos de fundación | E73: Ingreso | F73: 400 | G73: Cobrado | H73: AGL-NOT-DIL-006 | I73: Protocolización
A74: 46186 | B74: Junio | C74: Juan Navarrete | D74: Compraventa | E74: Ingreso | F74: 25 | G74: Cobrado | H74: AGL-NOT-VEH-001 | I74: Compraventa de vehículo
A75: 46186 | B75: Junio | C75: Varios | D75: Asesoría | E75: Ingreso | F75: 50 | G75: Cobrado | H75: AGL-ADM-REG-001 | I75: Gestión ante institución pública
A76: 46188 | B76: Junio | C76: Karla Reyes | D76: Aceptación de herencia | E76: Ingreso | F76: 50 | G76: Cobrado | H76: AGL-NOT-PAT-002 | I76: Aceptación de herencia notarial
A77: 46196 | B77: Junio | C77: Marvin Villalta | D77: Autorización | E77: Ingreso | F77: 25 | G77: Cobrado | H77: AGL-NOT-AUT-004 | I77: Acta notarial
A78: 46196 | B78: Junio | C78: CMC | D78: Acta notarial y traducción | E78: Ingreso | F78: 900 | G78: Cobrado | H78: AGL-NOT-DIL-001 | I78: Diligencia de traducción
A79: 46196 | B79: Junio | C79: Orison López | D79: Asesoría en familia | E79: Ingreso | F79: 50 | G79: Cobrado | H79: AGL-FAM-CUI-001 | I79: Acuerdo de cuidado personal
A80: 46196 | B80: Junio | C80: Joel Alvarado | D80: Contrato de arrendamiento | E80: Ingreso | F80: 20 | G80: Cobrado | H80: AGL-INM-ARR-001 | I80: Contrato de arrendamiento residencial
... A83: 46203 | B83: Junio | C83: SIAGRO | D83: Autorización salida de vehículo | E83: Ingreso | F83: 25 | G83: Cobrado | H83: AGL-NOT-VEH-003 | I83: Autorización de salida de vehículo
A84: 46203 | B84: Junio | D84: Insumos y publicaciones | E84: Egreso | F84: 25.72 | G84: Pagado | J84: Resumen reconstruido del archivo fuente
A85: 46203 | B85: Junio | D85: Salario Guadalupe | E85: Egreso | F85: 550 | G85: Pagado | J85: Resumen reconstruido del archivo fuente
A86: 46203 | B86: Junio | D86: Viáticos | E86: Egreso | F86: 30 | G86: Pagado | J86: Resumen reconstruido del archivo fuente
A87: 46203 | B87: Junio | D87: Traducciones tercero | E87: Egreso | F87: 70 | G87: Pagado | J87: Resumen reconstruido del archivo fuente
A88: 46203 | B88: Junio | D88: Arrendamiento local | E88: Egreso | F88: 575 | G88: Pagado | J88: Resumen reconstruido del archivo fuente
A89: 46204 | B89: Julio | C89: SIAGRO | D89: Autorización salida de vehículo | E89: Ingreso | F89: 25 | G89: Cobrado | H89: AGL-NOT-VEH-003 | I89: Autorización de salida de vehículo
A90: 46205 | B90: Julio | C90: Orison López | D90: Revisión de contrato | E90: Ingreso | F90: 120 | G90: Cobrado | H90: AGL-COR-CON-001 | I90: Revisión de contrato empresarial
A91: 46206 | B91: Julio | C91: Marvin Villalta | D91: Declaración jurada | E91: Ingreso | F91: 25 | G91: Cobrado | H91: AGL-NOT-AUT-003 | I91: Declaración jurada
A92: 46206 | B92: Julio | C92: Margarita Vaquerano | D92: Contrato de arrendamiento | E92: Ingreso | F92: 35 | G92: Cobrado | H92: AGL-INM-ARR-001 | I92: Contrato de arrendamiento residencial
A93: 46206 | B93: Julio | C93: Mariano Bonilla | D93: Contrato de arrendamiento | E93: Ingreso | F93: 35 | G93: Cobrado | H93: AGL-INM-ARR-001 | I93: Contrato de arrendamiento residencial
A94: 46206 | B94: Julio | C94: Ronald Rojas | D94: Auténtica de firma | E94: Ingreso | F94: 10 | G94: Cobrado | H94: AGL-NOT-AUT-001 | I94: Auténtica de firma
A95: 46206 | B95: Julio | C95: Andre Pranckevicius | D95: Investigación registral | E95: Ingreso | F95: 50 | G95: Cobrado | H95: AGL-INM-REG-001 | I95: Investigación registral
A96: 46218 | B96: Julio | C96: Daniel Martínez | D96: Resciliación y finiquito | E96: Ingreso | F96: 50 | G96: Cobrado | H96: AGL-NOT-CON-004 | I96: Resciliación y finiquito
A97: 46234 | B97: Julio | D97: Publicaciones y carencia | E97: Egreso | F97: 102.47 | G97: Pagado | J97: Resumen reconstruido del archivo fuente
A98: 46234 | B98: Julio | D98: Costo directo herencia Christine | E98: Egreso | F98: 102.47 | G98: Pagado | J98: Resumen reconstruido del archivo fuente
A99: 46234 | B99: Julio | D99: Arrendamiento local | E99: Egreso | F99: 575 | G99: Pagado | J99: Resumen reconstruido del archivo fuente
A100: 46234 | B100: Julio | D100: Internet | E100: Egreso | F100: 30 | G100: Pagado | J100: Resumen reconstruido del archivo fuente
A101: 46234 | B101: Julio | D101: Honorarios Guadalupe | E101: Egreso | F101: 550 | G101: Pagado | J101: Resumen reconstruido del archivo fuente

Sheet 05_Cartera_Proyectos
A1: 05 | Cartera y proyectos en ejecución
A2: Los importes pendientes no se consideran efectivo hasta ser cobrados. El cobro ponderado ajusta por probabilidad.
A4: ID | B4: Cliente | C4: Servicio / proyecto | D4: Código servicio | E4: Honorarios totales ($) | F4: Cobrado ($) | G4: Saldo pendiente ($) | H4: Estado | I4: Mes esperado | J4: Probabilidad | K4: Cobro ponderado ($) | L4: Próxima acción
A5: CAR-001 | B5: Ligia Carmona | C5: Compraventa e hipoteca | D5: AGL-NOT-INM-001 | E5: 350 | F5: 0 | G5: 350 | H5: En ejecución | I5: Julio | J5: 0.9 | K5: =G5*J5 -> 315 | L5: Finalizar documentos y gestionar cobro
A6: CAR-002 | B6: Ingrid Moreno | C6: Compraventa | D6: AGL-NOT-INM-001 | E6: 350 | F6: 0 | G6: 350 | H6: En ejecución | I6: Julio | J6: 0.9 | K6: =G6*J6 -> 315 | L6: Finalizar e inscribir
A7: CAR-003 | B7: Inocencia Villatoro | C7: Compraventa | D7: AGL-NOT-INM-001 | E7: 250 | F7: 0 | G7: 250 | H7: En ejecución | I7: Julio | J7: 0.85 | K7: =G7*J7 -> 212.5 | L7: Completar expediente
A8: CAR-004 | B8: Inocencia Canales | C8: Compraventa de terreno | D8: AGL-NOT-INM-001 | E8: 0 | F8: 0 | G8: 0 | H8: Pendiente de cotización | I8: Agosto | J8: 0.5 | K8: =G8*J8 -> 0 | L8: Definir honorarios
A9: CAR-005 | B9: Magdalena Wrobel | C9: Contrato | D9: AGL-CON-CIV-001 | E9: 150 | F9: 0 | G9: 150 | H9: En ejecución | I9: Julio | J9: 0.85 | K9: =G9*J9 -> 127.5 | L9: Finalizar y cobrar
A10: CAR-006 | B10: David Juárez | C10: Remedición - primer 50% | D10: AGL-NOT-DIL-002 | E10: 350 | F10: 175 | G10: 175 | H10: En ejecución | I10: Julio | J10: 0.95 | K10: =G10*J10 -> 166.25 | L10: Cobrar segundo 50%
A11: CAR-007 | B11: David Juárez | C11: Aceptación de herencia | D11: AGL-NOT-PAT-002 | E11: 1500 | F11: 200 | G11: 1300 | H11: En ejecución | I11: Agosto | J11: 0.9 | K11: =G11*J11 -> 1170 | L11: Corrección: $200 cobrado, $1,300 pendiente
A12: CAR-008 | B12: Christine Miranda | C12: Pago final aceptación de herencia | D12: AGL-NOT-PAT-002 | E12: 750 | F12: 0 | G12: 750 | H12: En ejecución | I12: Julio | J12: 0.95 | K12: =G12*J12 -> 712.5 | L12: Finalizar para cobrar
A13: CAR-009 | B13: Christine Miranda | C13: Fee mensual por horas | E13: 0 | F13: 0 | G13: 0 | H13: Pendiente de cuantificar | I13: Agosto | J13: 0.6 | K13: =G13*J13 -> 0 | L13: Registrar horas y emitir cobro

Sheet 06_Personal
A1: 06 | Salarios y honorarios mensuales
A2: Salarios objetivo que AG Legal debe cubrir desde julio hasta diciembre de 2026.
A4: Código | B4: Persona | C4: Cargo | D4: Monto mensual ($) | E4: Mes inicio | F4: Mes fin | G4: Meses 2026 | H4: Costo Jul-Dic ($)
A5: PER-001 | B5: Guadalupe Sánchez | C5: Abogada asociada | D5: 550 | E5: 7 | F5: 12 | G5: 6 | H5: =D5*G5 -> 3300
A6: PER-002 | B6: Alfredo Gallegos | C6: Abogado y notario | D6: 550 | E6: 7 | F6: 12 | G6: 6 | H6: =D6*G6 -> 3300
A7: PER-003 | B7: Andrea Escobar | C7: Manager / Desarrollo de Negocios | D7: 250 | E7: 7 | F7: 12 | G7: 6 | H7: =D7*G7 -> 1500
A9: Indicador | B9: Mensual | C9: Jul-Dic
A10: Total salarios | B10: =SUM(D5:D7) -> 1350 | C10: =SUM(H5:H7) -> 8100

Sheet 07_Gastos_Fijos
A1: 07 | Gastos fijos y supuestos
A2: Los valores en azul son editables. El modelo parte de los costos identificados en julio.
A4: Código | B4: Concepto | C4: Tipo | D4: Monto mensual ($) | E4: Mes inicio | F4: Mes fin | G4: Meses | H4: Costo Jul-Dic ($)
A5: GF-001 | B5: Salarios | C5: Fijo | D5: 1350 | E5: 7 | F5: 12 | G5: 6 | H5: =D5*G5 -> 8100
A6: GF-002 | B6: Arrendamiento local | C6: Fijo | D6: 575 | E6: 7 | F6: 12 | G6: 6 | H6: =D6*G6 -> 3450
A7: GF-003 | B7: Internet | C7: Fijo | D7: 30 | E7: 7 | F7: 12 | G7: 6 | H7: =D7*G7 -> 180
A8: GF-004 | B8: Otros gastos administrativos | C8: Estimado | D8: 150 | E8: 7 | F8: 12 | G8: 6 | H8: =D8*G8 -> 900
A9: GF-005 | B9: Marketing y captación | C9: Meta | D9: 150 | E9: 8 | F9: 12 | G9: 5 | H9: =D9*G9 -> 750
A11: Supuesto variable | B11: Valor
A12: Costo directo variable sobre ventas | B12: 0.1
A13: Margen operativo meta | B13: 0.2
A14: Margen de seguridad sobre punto de equilibrio | B14: 0.15
A16: Compensación variable | B16: Tratamiento | C16: Base | D16: Tasa | E16: Reconocimiento | F16: Clasificación | G16: Incluida en punto de equilibrio | H16: Observación
A17: Comisión Andrea | B17: Costo variable comercial | C17: Utilidad directa cobrada | D17: 5%-15% | E17: Al cobrar | F17: Variable | G17: No | H17: Debe calcularse en el sistema, no como gasto fijo
A18: Salario Andrea | B18: Costo fijo | C18: Mensual | D18: $250 | E18: Mensual | F18: Fijo | G18: Sí | H18: Ya incluido en salarios
A19: Regla | B19: No proyectar comisión sobre honorarios contratados o cartera no cobrada

Sheet 08_Presupuesto_Jul_Dic
A1: 08 | Proyección comercial por tipo de servicio | Julio–Diciembre 2026
A2: La proyección se construye por familias de servicios: volumen esperado × ticket objetivo. No se distribuyen ventas por persona. Los salarios se tratan únicamente como costos fijos.
A4: Código familia | B4: Familia de servicios | C4: Servicios incluidos | D4: Casos históricos | E4: Ingresos históricos ($) | F4: Ticket histórico ($) | G4: Ticket objetivo ($) | H4: Margen directo estimado % | I4: Jul Cant. | J4: Jul Ingreso ($) | K4: Ago Cant. | L4: Ago Ingreso ($) | M4: Sep Cant. | N4: Sep Ingreso ($) | O4: Oct Cant. | P4: Oct Ingreso ($) | Q4: Nov Cant. | R4: Nov Ingreso ($) | S4: Dic Cant. | T4: Dic Ingreso ($) | U4: Total casos | V4: Total ingresos ($)
A5: FAM-01 | B5: Notariales rápidos | C5: Actas, auténticas, declaraciones, autorizaciones, certificaciones y compraventas de vehículo | D5: 18 | E5: 430 | F5: 23.89 | G5: 35 | H5: 0.85 | I5: 4 | J5: 140 | K5: 10 | L5: =K5*$G5 -> 350 | M5: 11 | N5: =M5*$G5 -> 385 | O5: 12 | P5: =O5*$G5 -> 420 | Q5: 13 | R5: =Q5*$G5 -> 455 | S5: 14 | T5: =S5*$G5 -> 490 | U5: =SUM(I5,K5,M5,O5,Q5,S5) -> 64 | V5: =SUM(J5,L5,N5,P5,R5,T5) -> 2240
A6: FAM-02 | B6: Asesorías, contratos y gestiones | C6: Asesorías, escritos, arrendamientos, revisión contractual y acompañamientos administrativos | D6: 20 | E6: 1480 | F6: 74 | G6: 85 | H6: 0.9 | I6: 4 | J6: 340 | K6: 8 | L6: =K6*$G6 -> 680 | M6: 9 | N6: =M6*$G6 -> 765 | O6: 9 | P6: =O6*$G6 -> 765 | Q6: 10 | R6: =Q6*$G6 -> 850 | S6: 10 | T6: =S6*$G6 -> 850 | U6: =SUM(I6,K6,M6,O6,Q6,S6) -> 50 | V6: =SUM(J6,L6,N6,P6,R6,T6) -> 4250
A7: FAM-03 | B7: Inmobiliario y registral | C7: Compraventas de inmueble, promesas, hipotecas, investigaciones registrales y remediciones | D7: 9 | E7: 830 | F7: 92.22 | G7: 300 | H7: 0.88 | I7: 5 | J7: 1300 | K7: 3 | L7: =K7*$G7 -> 900 | M7: 3 | N7: =M7*$G7 -> 900 | O7: 3 | P7: =O7*$G7 -> 900 | Q7: 3 | R7: =Q7*$G7 -> 900 | S7: 4 | T7: =S7*$G7 -> 1200 | U7: =SUM(I7,K7,M7,O7,Q7,S7) -> 21 | V7: =SUM(J7,L7,N7,P7,R7,T7) -> 6100
A8: FAM-04 | B8: Herencias y planificación patrimonial | C8: Aceptaciones de herencia, cesiones de derechos, publicaciones y trámites sucesorios | D8: 4 | E8: 250 | F8: 62.5 | G8: 750 | H8: 0.82 | I8: 1 | J8: 750 | K8: 2 | L8: =K8*$G8 -> 1500 | M8: 1 | N8: =M8*$G8 -> 750 | O8: 1 | P8: =O8*$G8 -> 750 | Q8: 1 | R8: =Q8*$G8 -> 750 | S8: 1 | T8: =S8*$G8 -> 750 | U8: =SUM(I8,K8,M8,O8,Q8,S8) -> 7 | V8: =SUM(J8,L8,N8,P8,R8,T8) -> 5250
A9: FAM-05 | B9: Corporativo y administrativo especializado | C9: Protocolizaciones, OPAMSS, trámites complejos, conciliaciones y servicios empresariales | D9: 5 | E9: 650 | F9: 130 | G9: 350 | H9: 0.88 | I9: 1 | J9: 350 | K9: 1 | L9: =K9*$G9 -> 350 | M9: 1 | N9: =M9*$G9 -> 350 | O9: 1 | P9: =O9*$G9 -> 350 | Q9: 1 | R9: =Q9*$G9 -> 350 | S9: 1 | T9: =S9*$G9 -> 350 | U9: =SUM(I9,K9,M9,O9,Q9,S9) -> 6 | V9: =SUM(J9,L9,N9,P9,R9,T9) -> 2100
A10: FAM-06 | B10: Migración, relocalización y servicios internacionales | C10: NIT, residencias, acompañamiento migratorio, traducciones y relocalización | D10: 2 | E10: 945 | F10: 472.5 | G10: 500 | H10: 0.82 | I10: 0 | J10: 0 | K10: 1 | L10: =K10*$G10 -> 500 | M10: 1 | N10: =M10*$G10 -> 500 | O10: 1 | P10: =O10*$G10 -> 500 | Q10: 1 | R10: =Q10*$G10 -> 500 | S10: 1 | T10: =S10*$G10 -> 500 | U10: =SUM(I10,K10,M10,O10,Q10,S10) -> 5 | V10: =SUM(J10,L10,N10,P10,R10,T10) -> 2500
A11: TOTAL PROYECCIÓN POR SERVICIOS | D11: =SUM(D5:D10) -> 58 | E11: =SUM(E5:E10) -> 4585 | F11: =IFERROR(E11/D11,0) -> 79.051724 | G11: =IFERROR(V11/U11,0) -> 146.66667 | H11: =SUMPRODUCT(V5:V10,H5:H10)/V11 -> 0.8600713 | I11: =SUM(I5:I10) -> 15 | J11: =SUM(J5:J10) -> 2880 | K11: =SUM(K5:K10) -> 25 | L11: =SUM(L5:L10) -> 4280 | M11: =SUM(M5:M10) -> 26 | N11: =SUM(N5:N10) -> 3650 | O11: =SUM(O5:O10) -> 27 | P11: =SUM(P5:P10) -> 3685 | ... V11: =SUM(V5:V10) -> 22440
A14: Resultado mensual | B14: Julio | C14: Agosto | D14: Septiembre | E14: Octubre | F14: Noviembre | G14: Diciembre
A15: Ingresos proyectados por servicios | B15: =J$11 -> 2880 | C15: =L$11 -> 4280 | D15: =N$11 -> 3650 | E15: =P$11 -> 3685 | F15: =R$11 -> 3805 | G15: =T$11 -> 4140
A16: Costos directos estimados | B16: =SUMPRODUCT(J$5:J$10,1-$H$5:$H$10) -> 388 | C16: =SUMPRODUCT(L$5:L$10,1-$H$5:$H$10) -> 630.5 | D16: =SUMPRODUCT(N$5:N$10,1-$H$5:$H$10) -> 509.25 | E16: =SUMPRODUCT(P$5:P$10,1-$H$5:$H$10) -> 514.5 | F16: =SUMPRODUCT(R$5:R$10,1-$H$5:$H$10) -> 528.25 | G16: =SUMPRODUCT(T$5:T$10,1-$H$5:$H$10) -> 569.5
A17: Margen de contribución | B17: =B15-B16 -> 2492 | C17: =C15-C16 -> 3649.5 | D17: =D15-D16 -> 3140.75 | E17: =E15-E16 -> 3170.5 | F17: =F15-F16 -> 3276.75 | G17: =G15-G16 -> 3570.5
A18: Gastos fijos mensuales | B18: =SUM('07_Gastos_Fijos'!$D$5:$D$9) -> 2255 | C18: =SUM('07_Gastos_Fijos'!$D$5:$D$9) -> 2255 | D18: =SUM('07_Gastos_Fijos'!$D$5:$D$9) -> 2255 | E18: =SUM('07_Gastos_Fijos'!$D$5:$D$9) -> 2255 | F18: =SUM('07_Gastos_Fijos'!$D$5:$D$9) -> 2255 | G18: =SUM('07_Gastos_Fijos'!$D$5:$D$9) -> 2255
A19: Utilidad operativa | B19: =B17-B18 -> 237 | C19: =C17-C18 -> 1394.5 | D19: =D17-D18 -> 885.75 | E19: =E17-E18 -> 915.5 | F19: =F17-F18 -> 1021.75 | G19: =G17-G18 -> 1315.5
A20: Margen operativo % | B20: =IFERROR(B19/B15,0) -> 0.082291667 | C20: =IFERROR(C19/C15,0) -> 0.32581776 | D20: =IFERROR(D19/D15,0) -> 0.24267123 | E20: =IFERROR(E19/E15,0) -> 0.24843962 | F20: =IFERROR(F19/F15,0) -> 0.26852825 | G20: =IFERROR(G19/G15,0) -> 0.31775362
A21: Diferencia vs. punto de equilibrio | B21: =B15-'09_Punto_Equilibrio'!$B$7 -> 374.44444 | C21: =C15-'09_Punto_Equilibrio'!$B$7 -> 1774.4444 | D21: =D15-'09_Punto_Equilibrio'!$B$7 -> 1144.4444 | E21: =E15-'09_Punto_Equilibrio'!$B$7 -> 1179.4444 | F21: =F15-'09_Punto_Equilibrio'!$B$7 -> 1299.4444 | G21: =G15-'09_Punto_Equilibrio'!$B$7 -> 1634.4444

Sheet 09_Punto_Equilibrio
A1: 09 | Punto de equilibrio y metas mínimas
A2: Calcula cuánto debe cobrarse mensualmente para cubrir costos y generar utilidad.
A4: Indicador | B4: Resultado
A5: Gastos fijos mensuales | B5: =SUM('07_Gastos_Fijos'!D5:D9) -> 2255
A6: Costo variable % | B6: ='07_Gastos_Fijos'!B12 -> 0.1
A7: Punto de equilibrio de ventas | B7: =B5/(1-B6) -> 2505.5556
A8: Meta con margen de seguridad | B8: =B7*(1+'07_Gastos_Fijos'!B14) -> 2881.3889
A9: Ventas para margen operativo meta | B9: =B5/(1-B6-'07_Gastos_Fijos'!B13) -> 3221.4286
A10: Salarios cubiertos por las ventas meta | B10: =B9/'06_Personal'!B10 -> 2.3862434
A12: Ejemplo de mezcla mínima | B12: Cantidad | C12: Ticket promedio ($) | D12: Ingresos ($) | E12: Objetivo | F12: Comentario
A13: Servicios rápidos notariales | B13: 10 | C13: 35 | D13: =B13*C13 -> 350 | E13: Flujo inmediato | F13: Poderes, auténticas, declaraciones
A14: Contratos / asesorías | B14: 8 | C14: 75 | D14: =B14*C14 -> 600 | E14: Frecuencia | F14: Contratos, revisiones y acompañamientos
A15: Operaciones inmobiliarias | B15: 3 | C15: 300 | D15: =B15*C15 -> 900 | E15: Margen | F15: Compraventas, hipotecas y promesas
A16: Herencia / proceso de mayor valor | B16: 1 | C16: 750 | D16: =B16*C16 -> 750 | E16: Ticket alto | F16: Cobro por etapas
A17: TOTAL | D17: =SUM(D13:D16) -> 2600

Sheet 10_Dashboard
A1: 10 | Dashboard ejecutivo
A2: Vista rápida de cobros, cartera, punto de equilibrio y utilidad proyectada.
A4: COBRADO MAR-JUL | E4: CARTERA PENDIENTE | I4: PUNTO DE EQUILIBRIO | M4: META SEGURA
A5: =SUMIFS('04_Registro_Operaciones'!$F$5:$F$300,'04_Registro_Operaciones'!$E$5:$E$300,"Ingreso") -> 5515.5 | E5: =SUM('05_Cartera_Proyectos'!$G$5:$G$100) -> 3325 | I5: ='09_Punto_Equilibrio'!B7 -> 2505.5556 | M5: ='09_Punto_Equilibrio'!B8 -> 2881.3889
A9: Mes | B9: Ingresos proyectados ($) | C9: Utilidad operativa ($)
A10: Julio | B10: ='08_Presupuesto_Jul_Dic'!B15 -> 2880 | C10: ='08_Presupuesto_Jul_Dic'!B19 -> 237
A11: Agosto | B11: ='08_Presupuesto_Jul_Dic'!C15 -> 4280 | C11: ='08_Presupuesto_Jul_Dic'!C19 -> 1394.5
A12: Septiembre | B12: ='08_Presupuesto_Jul_Dic'!D15 -> 3650 | C12: ='08_Presupuesto_Jul_Dic'!D19 -> 885.75
A13: Octubre | B13: ='08_Presupuesto_Jul_Dic'!E15 -> 3685 | C13: ='08_Presupuesto_Jul_Dic'!E19 -> 915.5
A14: Noviembre | B14: ='08_Presupuesto_Jul_Dic'!F15 -> 3805 | C14: ='08_Presupuesto_Jul_Dic'!F19 -> 1021.75
A15: Diciembre | B15: ='08_Presupuesto_Jul_Dic'!G15 -> 4140 | C15: ='08_Presupuesto_Jul_Dic'!G19 -> 1315.5
A27: REQUERIMIENTOS PARA IMPLEMENTACIÓN EN EL SISTEMA
A28: Indicador | B28: Fuente | C28: Cálculo | D28: Actualización | E28: Filtro mínimo | F28: Drill-down
A29: Cumplimiento ingresos | B29: Cobros + forecast | C29: Ingresos cobrados / meta | D29: Automática | E29: Mes, categoría | F29: Expedientes
A30: Cumplimiento casos | B30: Expedientes + forecast | C30: Casos reales / meta casos | D30: Automática | E30: Mes, familia | F30: Servicios
A31: Utilidad operativa | B31: Cobros + costos + gastos + comisión | C31: Ingresos - costos - gastos - comisión | D31: Automática | E31: Mes | F31: P&L
A32: Comisión Andrea | B32: Origen + cobro + utilidad directa | C32: Escala 10%-12%-15% o 5% cross-sell | D32: Automática al cobrar | E32: Mes, expediente | F32: Detalle de comisión
A33: Servicios frecuentes/rentables | B33: Expedientes + cobros | C33: Frecuencia, utilidad directa y margen | D33: Automática | E33: Categoría, servicio | F33: Código servicio
A36: RESUMEN DE CUMPLIMIENTO MENSUAL
A37: Mes | B37: Meta ingresos | C37: Ingresos reales | D37: Cumplimiento | E37: Utilidad operativa real | F37: Utilidad mínima | G37: Semáforo
A38: ='17_Resumen_Mensual'!A5 -> Julio | B38: ='17_Resumen_Mensual'!B5 -> 3080 | C38: ='17_Resumen_Mensual'!C5 -> 350 | D38: ='17_Resumen_Mensual'!D5 -> 0.11363636 | E38: ='17_Resumen_Mensual'!J5 -> -1905 | F38: ='17_Resumen_Mensual'!K5 -> 616 | G38: ='17_Resumen_Mensual'!O5 -> ROJO
A39: ='17_Resumen_Mensual'!A6 -> Agosto | B39: ='17_Resumen_Mensual'!B6 -> 4280 | C39: ='17_Resumen_Mensual'!C6 -> 0 | D39: ='17_Resumen_Mensual'!D6 -> 0 | E39: ='17_Resumen_Mensual'!J6 -> -2255 | F39: ='17_Resumen_Mensual'!K6 -> 856 | G39: ='17_Resumen_Mensual'!O6 -> ROJO
A40: ='17_Resumen_Mensual'!A7 -> Septiembre | B40: ='17_Resumen_Mensual'!B7 -> 3650 | C40: ='17_Resumen_Mensual'!C7 -> 0 | D40: ='17_Resumen_Mensual'!D7 -> 0 | E40: ='17_Resumen_Mensual'!J7 -> -2255 | F40: ='17_Resumen_Mensual'!K7 -> 730 | G40: ='17_Resumen_Mensual'!O7 -> ROJO
A41: ='17_Resumen_Mensual'!A8 -> Octubre | B41: ='17_Resumen_Mensual'!B8 -> 3685 | C41: ='17_Resumen_Mensual'!C8 -> 0 | D41: ='17_Resumen_Mensual'!D8 -> 0 | E41: ='17_Resumen_Mensual'!J8 -> -2255 | F41: ='17_Resumen_Mensual'!K8 -> 737 | G41: ='17_Resumen_Mensual'!O8 -> ROJO
A42: ='17_Resumen_Mensual'!A9 -> Noviembre | B42: ='17_Resumen_Mensual'!B9 -> 3805 | C42: ='17_Resumen_Mensual'!C9 -> 0 | D42: ='17_Resumen_Mensual'!D9 -> 0 | E42: ='17_Resumen_Mensual'!J9 -> -2255 | F42: ='17_Resumen_Mensual'!K9 -> 761 | G42: ='17_Resumen_Mensual'!O9 -> ROJO
A43: ='17_Resumen_Mensual'!A10 -> Diciembre | B43: ='17_Resumen_Mensual'!B10 -> 4140 | C43: ='17_Resumen_Mensual'!C10 -> 0 | D43: ='17_Resumen_Mensual'!D10 -> 0 | E43: ='17_Resumen_Mensual'!J10 -> -2255 | F43: ='17_Resumen_Mensual'!K10 -> 828 | G43: ='17_Resumen_Mensual'!O10 -> ROJO

Sheet 11_Listas
A1: 11 | Listas de control
A2: Valores auxiliares para el sistema.
A4: Estado servicio | B4: Unidad cobro | C4: Estado cartera | D4: Mes | E4: Tipo operación | F4: Responsable
A5: Activo | B5: Precio fijo | C5: Pendiente de cotización | D5: Julio | E5: Ingreso | F5: Socio / Notario
A6: Inactivo | B6: Por hora | C6: Pendiente de cuantificar | D6: Agosto | E6: Egreso | F6: Abogada asociada
A7: En diseño | B7: Por etapa | C7: En ejecución | D7: Septiembre | F7: Manager
B8: Mensual | C8: Finalizado pendiente de facturar | D8: Octubre | F8: Asistente legal
B9: Porcentaje | C9: Facturado pendiente de cobro | D9: Noviembre | F9: Equipo mixto
B10: Por definir | C10: Cobrado | D10: Diciembre | F10: Por definir
C11: Suspendido

Sheet 12_Reglas_Comision
A1: 12 | Reglas de compensación variable de Comercial
A2: La compensación se calcula únicamente sobre utilidad directa efectivamente cobrada de negocios originados o ampliados por Andrea.
A4: Regla ID | B4: Tipo de negocio | C4: Condición | D4: Base de cálculo | E4: Tramo desde ($) | F4: Tramo hasta ($) | G4: Porcentaje | H4: Momento de reconocimiento | I4: Exclusiones | J4: Responsable de validación | K4: Estado
A5: COM-001 | B5: Cliente nuevo originado y cerrado por Andrea | C5: Andrea identifica, desarrolla, cotiza o coordina la propuesta y logra la aceptación del cliente. | D5: Utilidad directa cobrada | E5: 0 | F5: 1000 | G5: 0.1 | H5: Al cobrarse efectivamente el honorario | I5: IVA, tasas, publicaciones, derechos registrales, gastos reembolsables, fondos de terceros y devoluciones | J5: Administración / Socio | K5: Activo
A6: COM-002 | B6: Cliente nuevo originado y cerrado por Andrea | C6: Segundo tramo mensual acumulado de utilidad directa originada. | D6: Utilidad directa cobrada | E6: 1000.01 | F6: 2500 | G6: 0.12 | H6: Al cobrarse efectivamente el honorario | I6: IVA, tasas, publicaciones, derechos registrales, gastos reembolsables, fondos de terceros y devoluciones | J6: Administración / Socio | K6: Activo
A7: COM-003 | B7: Cliente nuevo originado y cerrado por Andrea | C7: Tercer tramo mensual acumulado de utilidad directa originada. | D7: Utilidad directa cobrada | E7: 2500.01 | F7: 9999999 | G7: 0.15 | H7: Al cobrarse efectivamente el honorario | I7: IVA, tasas, publicaciones, derechos registrales, gastos reembolsables, fondos de terceros y devoluciones | J7: Administración / Socio | K7: Activo
A8: COM-004 | B8: Venta cruzada a cliente existente | C8: Andrea genera y cierra un servicio adicional para un cliente ya perteneciente a AG Legal. | D8: Utilidad directa cobrada | E8: 0 | F8: 9999999 | G8: 0.05 | H8: Al cobrarse efectivamente el honorario | I8: Servicios ya contratados, renovaciones automáticas y simples seguimientos administrativos | J8: Administración / Socio | K8: Activo
A10: Concepto | B10: Definición funcional
A11: Honorario cobrado | B11: Importe neto efectivamente recibido por AG Legal por el servicio.
A12: Costo directo | B12: Costo atribuible al expediente: terceros, gestor, transporte específico, traducción, publicación o insumo particular.
A13: Utilidad directa | B13: Honorario cobrado menos costo directo atribuible al servicio.
A14: Negocio originado | B14: Cliente o asunto nuevo conseguido por Andrea y registrado con evidencia de origen.
A15: Venta cruzada | B15: Servicio nuevo vendido a un cliente existente de la firma.
A16: Fecha de comisión | B16: Mes en el que el efectivo se recibe, no la fecha de cotización o contratación.
A17: Reversión | B17: Si existe devolución o ajuste posterior, la comisión se corrige en el siguiente período.
A19: Ejemplo | B19: Utilidad directa mensual ($) | C19: 10% tramo 1 | D19: 12% tramo 2 | E19: 15% tramo 3 | F19: Comisión total ($)
A20: Caso A | B20: 600 | C20: =MIN(B20,1000)*10% -> 60 | D20: =MAX(MIN(B20-1000,1500),0)*12% -> 0 | E20: =MAX(B20-2500,0)*15% -> 0 | F20: =SUM(C20:E20) -> 60
A21: Caso B | B21: 1800 | C21: =MIN(B21,1000)*10% -> 100 | D21: =MAX(MIN(B21-1000,1500),0)*12% -> 96 | E21: =MAX(B21-2500,0)*15% -> 0 | F21: =SUM(C21:E21) -> 196
A22: Caso C | B22: 3000 | C22: =MIN(B22,1000)*10% -> 100 | D22: =MAX(MIN(B22-1000,1500),0)*12% -> 180 | E22: =MAX(B22-2500,0)*15% -> 75 | F22: =SUM(C22:E22) -> 355
A23: Caso D | B23: 4500 | C23: =MIN(B23,1000)*10% -> 100 | D23: =MAX(MIN(B23-1000,1500),0)*12% -> 180 | E23: =MAX(B23-2500,0)*15% -> 300 | F23: =SUM(C23:E23) -> 580
A24: Fórmula de referencia | B24: MIN(U,1000)*10% + MAX(MIN(U-1000,1500),0)*12% + MAX(U-2500,0)*15%

Sheet 13_Especificacion_Sistema
A1: 13 | ANEXO TÉCNICO — consultar después de 00_PARA_DESARROLLADOR
A2: Esta hoja conserva el detalle ampliado de campos. La hoja principal y obligatoria para iniciar la implementación es 00_PARA_DESARROLLADOR.
A4: Módulo | B4: Entidad / tabla | C4: Campo | D4: Tipo de dato | E4: Obligatorio | F4: Editable | G4: Fuente / relación | H4: Regla de validación | I4: Cálculo automático | J4: Uso en dashboard | K4: Histórico requerido | L4: Ejemplo | M4: Prioridad | N4: Observaciones
A5: Catálogo | B5: categorias | C5: codigo_categoria | D5: Texto 3-4 | E5: Sí | F5: No | G5: Maestro | H5: Único, mayúsculas, no reutilizable | J5: Filtro y agrupación | K5: Sí | L5: NOT | M5: Alta | N5: Clave primaria funcional
A6: Catálogo | B6: categorias | C6: nombre_categoria | D6: Texto | E6: Sí | F6: Sí | G6: Maestro | H6: Nombre único | J6: Etiqueta | K6: Sí | L6: Servicios Notariales | M6: Alta
A7: Catálogo | B7: subcategorias | C7: codigo_subcategoria | D7: Texto 3 | E7: Sí | F7: No | G7: Depende de categoría | H7: Único dentro de categoría | J7: Filtro y agrupación | K7: Sí | L7: INM | M7: Alta
A8: Catálogo | B8: servicios | C8: codigo_servicio | D8: Texto | E8: Sí | F8: No | G8: Categoría + subcategoría + secuencia | H8: Formato AGL-CAT-SUB-000 | J8: Búsqueda y drill-down | K8: Sí | L8: AGL-NOT-INM-001 | M8: Crítica | N8: Nunca reutilizar
A9: Catálogo | B9: servicios | C9: nombre_servicio | D9: Texto | E9: Sí | F9: Sí | G9: Maestro | H9: No duplicar prestación idéntica | J9: Ranking servicios | K9: Sí | L9: Escritura de compraventa | M9: Crítica
A10: Catálogo | B10: servicios | C10: etiquetas | D10: Texto múltiple | E10: No | F10: Sí | G10: Maestro | H10: Separadas por coma | J10: Búsqueda transversal | K10: Sí | L10: familia, inmueble, notarial | M10: Media
A11: Operaciones | B11: expedientes | C11: id_expediente | D11: Autonumérico | E11: Sí | F11: No | G11: Sistema | H11: Único | J11: Conteo casos | K11: Sí | L11: EXP-2026-0001 | M11: Crítica
A12: Operaciones | B12: expedientes | C12: cliente_id | D12: Relación | E12: Sí | F12: Sí | G12: Clientes | H12: Cliente válido | J12: Clientes nuevos/recurrentes | K12: Sí | L12: CLI-001 | M12: Crítica
A13: Operaciones | B13: expedientes | C13: codigo_servicio | D13: Relación | E13: Sí | F13: Sí | G13: Catálogo servicios | H13: Solo servicios activos | I13: Completa categoría y subcategoría | J13: Ventas por servicio | K13: Sí | L13: AGL-NOT-INM-001 | M13: Crítica
A14: Operaciones | B14: expedientes | C14: origen_negocio | D14: Lista | E14: Sí | F14: Sí | G14: Lista control | H14: Andrea / Alfredo / Guadalupe / Referido / Orgánico / Otro | J14: Ventas por origen | K14: Sí | L14: Andrea | M14: Crítica | N14: Base de comisión
A15: Operaciones | B15: expedientes | C15: tipo_origen | D15: Lista | E15: Sí | F15: Sí | G15: Lista control | H15: Cliente nuevo / Venta cruzada / Cliente existente | J15: Conversión y comisión | K15: Sí | L15: Cliente nuevo | M15: Crítica
A16: Operaciones | B16: expedientes | C16: honorarios_contratados | D16: Moneda | E16: Sí | F16: Sí | G16: Contrato/propuesta | H16: Mayor o igual a cero | J16: Pipeline y ticket | K16: Sí | L16: 750 | M16: Crítica | N16: Excluir IVA y reembolsos
A17: Operaciones | B17: expedientes | C17: costos_directos_estimados | D17: Moneda | E17: Sí | F17: Sí | G17: Presupuesto expediente | H17: Mayor o igual a cero | I17: Utilidad directa estimada | J17: Margen proyectado | K17: Sí | L17: 70 | M17: Alta
A18: Operaciones | B18: expedientes | C18: estado_expediente | D18: Lista | E18: Sí | F18: Sí | G18: Workflow | H18: Cotizado / Aceptado / En ejecución / Finalizado / Facturado / Cobrado / Suspendido | J18: Pipeline | K18: Sí | L18: En ejecución | M18: Crítica
A19: Operaciones | B19: expedientes | C19: mes_cobro_esperado | D19: Fecha mes | E19: Sí | F19: Sí | G19: Gestión | H19: No anterior a fecha de apertura | I19: Proyección mensual | J19: Forecast | K19: Sí | L19: 2026-08 | M19: Crítica
A20: Cobros | B20: cobros | C20: monto_honorario_cobrado | D20: Moneda | E20: Sí | F20: Sí | G20: Expediente | H20: No incluir IVA ni gastos de terceros | I20: Saldo pendiente | J20: Ingresos cobrados | K20: Sí | L20: 200 | M20: Crítica
A21: Cobros | B21: cobros | C21: fecha_cobro | D21: Fecha | E21: Sí | F21: Sí | G21: Banco/caja | H21: Fecha válida | I21: Mes real de ingreso | J21: Cumplimiento mensual | K21: Sí | L21: 2026-07-15 | M21: Crítica
A22: Cobros | B22: cobros | C22: monto_costo_directo_real | D22: Moneda | E22: Sí | F22: Sí | G22: Expediente | H22: Mayor o igual a cero | I22: Utilidad directa real | J22: Margen real | K22: Sí | L22: 25 | M22: Crítica
A23: Cobros | B23: cobros | C23: utilidad_directa_real | D23: Moneda | E23: Sí | F23: No | G23: Cobro - costo directo | H23: Puede ser negativa | I23: Honorario neto - costo directo | J23: Comisión y rentabilidad | K23: Sí | L23: 175 | M23: Crítica
A24: Comisión | B24: comisiones | C24: elegible_comision_andrea | D24: Booleano | E24: Sí | F24: Sí | G24: Origen y tipo de negocio | H24: Debe existir evidencia del origen | I24: Sí/No por reglas | J24: Comisión devengada | K24: Sí | L24: Sí | M24: Crítica
A25: Comisión | B25: comisiones | C25: porcentaje_aplicable | D25: Porcentaje | E25: Sí | F25: No | G25: Reglas COM-001 a COM-004 | H25: 5%, 10%, 12% o 15% | I25: Escalonado por mes | J25: Costo variable | K25: Sí | L25: 10% | M25: Crítica
A26: Comisión | B26: comisiones | C26: comision_devengada | D26: Moneda | E26: Sí | F26: No | G26: Utilidad directa cobrada | H26: Solo después del cobro | I26: Según tramos y venta cruzada | J26: Comisión mensual | K26: Sí | L26: 60 | M26: Crítica
A27: Proyección | B27: forecast | C27: volumen_meta | D27: Entero | E27: Sí | F27: Sí | G27: Familia + mes | H27: Mayor o igual a cero | I27: Volumen × ticket objetivo | J27: Cumplimiento de volumen | K27: Sí | L27: 3 | M27: Alta
A28: Proyección | B28: forecast | C28: ticket_objetivo | D28: Moneda | E28: Sí | F28: Sí | G28: Familia + mes | H28: Mayor o igual a cero | I28: Ingreso meta | J28: Cumplimiento de ingresos | K28: Sí | L28: 300 | M28: Alta
A29: Proyección | B29: forecast | C29: ingreso_proyectado | D29: Moneda | E29: Sí | F29: No | G29: Volumen × ticket | H29: Fórmula automática | I29: volumen_meta*ticket_objetivo | J29: Forecast mensual | K29: Sí | L29: 900 | M29: Crítica
A30: Proyección | B30: forecast | C30: probabilidad_cobro | D30: Porcentaje | E30: Sí | F30: Sí | G30: Estado expediente | H30: 0% a 100% | I30: Saldo pendiente × probabilidad | J30: Forecast ponderado | K30: Sí | L30: 90% | M30: Alta
A34: REQUISITOS ADICIONALES: PLAN DE CUENTAS Y MOVIMIENTOS
A35: Finanzas | B35: plan_cuentas | C35: codigo_cuenta | D35: Texto | E35: Sí | F35: No | G35: Plan de cuentas | H35: Único; formato ING-XXX-000 o EGR-XXX-000 | J35: Agrupación de ingresos y egresos | K35: Sí | L35: ING-RAI-001 | M35: Crítica | N35: Todo movimiento debe tener código de cuenta.
A36: Finanzas | B36: movimientos | C36: tipo_movimiento | D36: Lista | E36: Sí | F36: Sí | G36: Ingreso / Egreso | H36: Debe coincidir con el prefijo de código cuenta | J36: P&L y flujo | K36: Sí | L36: Ingreso | M36: Crítica | N36: ING solo para ingresos; EGR solo para egresos.
A37: Finanzas | B37: movimientos | C37: codigo_cuenta | D37: Relación | E37: Sí | F37: Sí | G37: Plan de cuentas | H37: Cuenta activa y compatible con tipo de movimiento | I37: Completa cuenta, grupo y centro de costo | J37: P&L por cuenta | K37: Sí | L37: EGR-LOC-001 | M37: Crítica
A38: Finanzas | B38: movimientos | C38: codigo_servicio | D38: Relación | E38: Condicional | F38: Sí | G38: Catálogo servicios | H38: Obligatorio para ingresos jurídicos y costos directos de expediente | I38: Completa categoría y subcategoría | J38: Rentabilidad por servicio | K38: Sí | L38: AGL-RAI-RGT-001 | M38: Crítica | N38: Puede quedar vacío para salarios o renta.
A39: Finanzas | B39: movimientos | C39: monto_bruto | D39: Moneda | E39: Sí | F39: Sí | G39: Documento fuente | H39: Mayor o igual a cero | I39: Monto neto operativo | J39: Ingresos y egresos | K39: Sí | L39: 350 | M39: Crítica
A40: Finanzas | B40: movimientos | C40: monto_reembolsable | D40: Moneda | E40: Sí | F40: Sí | G40: Expediente | H40: Mayor o igual a cero | I40: Excluir de utilidad y comisión | J40: Flujo de terceros | K40: Sí | L40: 23.75 | M40: Alta
A41: Finanzas | B41: movimientos | C41: monto_neto_operativo | D41: Moneda | E41: Sí | F41: No | G41: Bruto - IVA - reembolsable | H41: Fórmula automática | I41: monto_bruto-IVA-reembolsable | J41: P&L y comisión | K41: Sí | L41: 326.25 | M41: Crítica
A44: REQUISITOS DE GOBIERNO DEL CATÁLOGO
A45: Gobierno catálogo | B45: solicitudes_catalogo | C45: id_solicitud | D45: Texto | E45: Sí | F45: No | G45: Sistema | H45: Único y secuencial | I45: Generación automática | J45: Auditoría de cambios | K45: Sí | L45: SOL-2026-001 | M45: Crítica
A46: Gobierno catálogo | B46: solicitudes_catalogo | C46: tipo_solicitud | D46: Lista | E46: Sí | F46: Sí | G46: Alta/Modificación/Inactivación | H46: Valor permitido | J46: Análisis de cambios | K46: Sí | L46: Alta | M46: Alta
A47: Gobierno catálogo | B47: solicitudes_catalogo | C47: tipo_registro | D47: Lista | E47: Sí | F47: Sí | G47: Categoría/Subcategoría/Servicio | H47: Valor permitido | J47: Análisis de cambios | K47: Sí | L47: Servicio | M47: Crítica
A48: Gobierno catálogo | B48: solicitudes_catalogo | C48: resultado_duplicidad | D48: Texto | E48: Sí | F48: Sí | G48: Revisión del catálogo | H48: Debe completarse antes de aprobar | J48: Control interno | K48: Sí | L48: Sin duplicidad | M48: Crítica
A49: Gobierno catálogo | B49: solicitudes_catalogo | C49: estado_solicitud | D49: Lista | E49: Sí | F49: Sí | G49: Workflow | H49: Solicitado/En revisión/Aprobado/Rechazado/Activo/Inactivo | I49: Control de flujo | J49: Seguimiento | K49: Sí | L49: En revisión | M49: Crítica
A50: Gobierno catálogo | B50: historial_catalogo | C50: version_anterior | D50: JSON/Texto | E50: Sí | F50: No | G50: Registro previo | H50: Inmutable | I50: Guardar antes del cambio | J50: Auditoría | K50: Sí | M50: Alta
A51: Gobierno catálogo | B51: historial_catalogo | C51: usuario_cambio | D51: Relación | E51: Sí | F51: No | G51: Usuarios | H51: Usuario autenticado | I51: Automático | J51: Auditoría | K51: Sí | L51: USR-001 | M51: Crítica
A52: Gobierno catálogo | B52: historial_catalogo | C52: fecha_cambio | D52: Fecha/hora | E52: Sí | F52: No | G52: Sistema | H52: Timestamp automático | I52: Automático | J52: Auditoría | K52: Sí | L52: 2026-07-16 10:00 | M52: Crítica
A55: ACTUALIZACIÓN FUNCIONAL: DERECHO PENAL
A56: Catálogo | B56: categorias | C56: PEN | D56: Código fijo | E56: Sí | F56: No | G56: Maestro | H56: Categoría independiente; no registrar servicios penales bajo LIT. | J56: Filtro y rentabilidad penal | K56: Sí | L56: PEN | M56: Crítica | N56: LIT queda para controversias mercantiles, civiles, laborales y métodos alternos.
A57: Catálogo | B57: servicios | C57: codigo_servicio_penal | D57: Texto | E57: Sí | F57: No | G57: PEN + subcategoría + secuencia | H57: Formato AGL-PEN-SUB-000 | J57: Seguimiento por tipo penal | K57: Sí | L57: AGL-PEN-DEF-001 | M57: Crítica | N57: Toda actuación penal debe utilizar un código de la categoría PEN.
A58: Finanzas | B58: plan_cuentas | C58: ING-PEN-001 | D58: Código cuenta | E58: Sí | F58: No | G58: Plan de cuentas | H58: Usar en cobros por servicios penales | J58: Ingresos por categoría | K58: Sí | L58: ING-PEN-001 | M58: Crítica

Sheet 14_Dashboard_KPIs
A1: 14 | Requerimientos del dashboard
A2: Indicadores que el sistema debe calcular automáticamente a partir de expedientes, cobros, costos, cartera y metas.
A4: KPI ID | B4: Indicador | C4: Definición | D4: Fórmula funcional | E4: Frecuencia | F4: Filtros | G4: Visual recomendado | H4: Meta / semáforo | I4: Fuente principal | J4: Drill-down | K4: Prioridad | L4: Notas
A5: KPI-001 | B5: Ingresos cobrados | C5: Honorarios netos efectivamente recibidos en el período. | D5: SUM(monto_honorario_cobrado) | E5: Diaria / mensual | F5: Mes, categoría, subcategoría, servicio, origen | G5: Tarjeta + línea mensual | H5: Verde >= meta; amarillo 90%-99%; rojo <90% | I5: Cobros | J5: Lista de cobros | K5: Crítica | L5: Excluir IVA y reembolsos
A6: KPI-002 | B6: Ingresos proyectados | C6: Volumen meta por ticket objetivo, más cartera ponderada. | D6: SUM(volumen_meta*ticket_objetivo)+SUM(saldo_pendiente*probabilidad) | E6: Mensual | F6: Mes y familia | G6: Columnas meta vs real | H6: Comparar contra presupuesto | I6: Forecast + cartera | J6: Expedientes proyectados | K6: Crítica
A7: KPI-003 | B7: Cumplimiento de ingresos | C7: Porcentaje de ingresos cobrados contra meta mensual. | D7: Ingresos cobrados / Meta ingresos | E7: Diaria / mensual | F7: Mes, categoría | G7: Gauge o barra de progreso | H7: Verde >=100%; amarillo 85%-99%; rojo <85% | I7: Cobros + forecast | J7: Servicios del mes | K7: Crítica
A8: KPI-004 | B8: Punto de equilibrio | C8: Ventas necesarias para cubrir gastos fijos y costos variables. | D8: Gastos fijos / (1 - % costo variable) | E8: Mensual | F8: Mes | G8: Tarjeta y línea de referencia | H8: Verde si ingresos > punto equilibrio | I8: Gastos + supuestos | J8: Detalle costos | K8: Crítica
A9: KPI-005 | B9: Utilidad operativa | C9: Ingresos cobrados menos costos directos, gastos fijos y comisión. | D9: Ingresos - costos directos - gastos fijos - comisión | E9: Mensual | F9: Mes, categoría | G9: Tarjeta + tendencia | H9: Verde >0; rojo <0 | I9: Cobros + gastos + comisiones | J9: P&L mensual | K9: Crítica
A10: KPI-006 | B10: Margen operativo | C10: Utilidad operativa como porcentaje de ingresos cobrados. | D10: Utilidad operativa / Ingresos cobrados | E10: Mensual | F10: Mes, categoría | G10: Tarjeta porcentual | H10: Meta inicial 20% | I10: P&L | J10: Detalle mensual | K10: Alta
A11: KPI-007 | B11: Cartera pendiente | C11: Honorarios contratados aún no cobrados. | D11: SUM(honorarios_contratados - cobros) | E11: Diaria | F11: Estado, mes esperado, cliente | G11: Tarjeta + aging | H11: Rojo si vencida | I11: Expedientes + cobros | J11: Detalle expediente | K11: Crítica
A12: KPI-008 | B12: Cartera ponderada | C12: Saldo pendiente ajustado por probabilidad de cobro. | D12: SUM(saldo_pendiente*probabilidad) | E12: Diaria | F12: Mes esperado, estado | G12: Columnas por mes | H12: Comparar con meta | I12: Expedientes | J12: Detalle cartera | K12: Alta
A13: KPI-009 | B13: Ticket promedio | C13: Ingreso cobrado promedio por expediente o servicio. | D13: Ingresos cobrados / expedientes cobrados | E13: Mensual | F13: Categoría, servicio | G13: Tarjeta + ranking | H13: Comparar con ticket objetivo | I13: Cobros | J13: Expedientes cobrados | K13: Alta
A14: KPI-010 | B14: Servicios más frecuentes | C14: Número de expedientes por servicio. | D14: COUNT(expedientes) por código servicio | E14: Mensual | F14: Mes, categoría | G14: Top 10 barras | H14: Sin semáforo | I14: Expedientes | J14: Lista expedientes | K14: Alta
A15: KPI-011 | B15: Servicios más rentables | C15: Utilidad directa y margen por servicio. | D15: SUM(utilidad directa) y utilidad/ingreso | E15: Mensual | F15: Categoría, servicio | G15: Matriz frecuencia vs margen | H15: Priorizar alto margen y frecuencia | I15: Cobros + costos | J15: Detalle por código | K15: Crítica
A16: KPI-012 | B16: Conversión comercial | C16: Propuestas aceptadas sobre propuestas emitidas. | D16: Aceptadas / Cotizadas | E16: Mensual | F16: Origen, servicio | G16: Funnel | H16: Meta a definir | I16: Expedientes | J16: Cotizaciones | K16: Media
A17: KPI-013 | B17: Cumplimiento de volumen | C17: Casos reales contra volumen meta por familia. | D17: Casos abiertos o cobrados / volumen_meta | E17: Mensual | F17: Familia, mes | G17: Barras progreso | H17: Verde >=100% | I17: Expedientes + forecast | J17: Servicios de familia | K17: Alta
... A20: KPI-016 | B20: Días promedio de cobro | C20: Tiempo desde finalización o facturación hasta cobro. | D20: AVG(fecha_cobro - fecha_factura/finalización) | E20: Mensual | F20: Servicio, cliente | G20: Tarjeta + tendencia | H20: Menor es mejor | I20: Expedientes + cobros | J20: Aging | K20: Media

Sheet 15_Cumplimiento_Metas
A1: 15 | Metas mensuales, realidad y cumplimiento
A2: Las metas se definen por familia de servicio. Las columnas azules se llenan con la realidad mientras el sistema entra en operación; luego deberán alimentarse automáticamente.
A4: Mes | B4: Código familia | C4: Familia de servicios | D4: Meta casos | E4: Casos reales | F4: Cumplimiento casos % | G4: Ticket objetivo ($) | H4: Ticket real ($) | I4: Variación ticket % | J4: Meta ingresos ($) | K4: Ingresos reales ($) | L4: Cumplimiento ingresos % | M4: Margen directo objetivo % | N4: Costos directos reales ($) | O4: Utilidad directa real ($) | P4: Utilidad directa objetivo ($) | Q4: Cumplimiento utilidad directa % | R4: Asignación gastos fijos ($) | S4: Comisión Andrea ($) | T4: Utilidad operativa real ($) | U4: Margen operativo real % | V4: Semáforo
A5: Julio | B5: FAM-01 | C5: Notariales rápidos | D5: 4 | E5: 3 | F5: =IFERROR(E5/D5,0) -> 0.75 | G5: 35 | H5: =IFERROR(K5/E5,0) -> 20 | I5: =IFERROR(H5/G5-1,0) -> -0.42857143 | J5: 140 | K5: 60 | L5: =IFERROR(K5/J5,0) -> 0.42857143 | M5: 0.85 | N5: 0 | O5: =K5-N5 -> 60 | P5: 119 | Q5: =IFERROR(O5/P5,0) -> 0.50420168 | R5: =IFERROR(J5/SUM($J$5:$J$10)*SUM('07_Gastos_Fijos'!$D$5:$D$9),0) -> 102.5 | S5: 0 | T5: =O5-R5-S5 -> -42.5 | U5: =IFERROR(T5/K5,0) -> -0.70833333 | V5: =IF(L5>=1,"VERDE",IF(L5>=0.85,"AMARILLO","ROJO")) -> ROJO
A6: Julio | B6: FAM-02 | C6: Asesorías, contratos y gestiones | D6: 4 | E6: 4 | F6: =IFERROR(E6/D6,0) -> 1 | G6: 85 | H6: =IFERROR(K6/E6,0) -> 60 | I6: =IFERROR(H6/G6-1,0) -> -0.29411765 | J6: 340 | K6: 240 | L6: =IFERROR(K6/J6,0) -> 0.70588235 | M6: 0.9 | N6: 0 | O6: =K6-N6 -> 240 | P6: 306 | Q6: =IFERROR(O6/P6,0) -> 0.78431373 | R6: =IFERROR(J6/SUM($J$5:$J$10)*SUM('07_Gastos_Fijos'!$D$5:$D$9),0) -> 248.92857 | S6: 0 | T6: =O6-R6-S6 -> -8.9285714 | U6: =IFERROR(T6/K6,0) -> -0.037202381 | V6: =IF(L6>=1,"VERDE",IF(L6>=0.85,"AMARILLO","ROJO")) -> ROJO
A7: Julio | B7: FAM-03 | C7: Inmobiliario y registral | D7: 5 | E7: 1 | F7: =IFERROR(E7/D7,0) -> 0.2 | G7: 300 | H7: =IFERROR(K7/E7,0) -> 50 | I7: =IFERROR(H7/G7-1,0) -> -0.83333333 | J7: 1500 | K7: 50 | L7: =IFERROR(K7/J7,0) -> 0.033333333 | M7: 0.88 | N7: 0 | O7: =K7-N7 -> 50 | P7: 1320 | Q7: =IFERROR(O7/P7,0) -> 0.037878788 | R7: =IFERROR(J7/SUM($J$5:$J$10)*SUM('07_Gastos_Fijos'!$D$5:$D$9),0) -> 1098.2143 | S7: 0 | T7: =O7-R7-S7 -> -1048.2143 | U7: =IFERROR(T7/K7,0) -> -20.964286 | V7: =IF(L7>=1,"VERDE",IF(L7>=0.85,"AMARILLO","ROJO")) -> ROJO
A8: Julio | B8: FAM-04 | C8: Herencias y planificación patrimonial | D8: 1 | E8: 0 | F8: =IFERROR(E8/D8,0) -> 0 | G8: 750 | H8: =IFERROR(K8/E8,0) -> 0 | I8: =IFERROR(H8/G8-1,0) -> -1 | J8: 750 | K8: 0 | L8: =IFERROR(K8/J8,0) -> 0 | M8: 0.82 | N8: 0 | O8: =K8-N8 -> 0 | P8: 615 | Q8: =IFERROR(O8/P8,0) -> 0 | R8: =IFERROR(J8/SUM($J$5:$J$10)*SUM('07_Gastos_Fijos'!$D$5:$D$9),0) -> 549.10714 | S8: 0 | T8: =O8-R8-S8 -> -549.10714 | U8: =IFERROR(T8/K8,0) -> 0 | V8: =IF(L8>=1,"VERDE",IF(L8>=0.85,"AMARILLO","ROJO")) -> ROJO
A9: Julio | B9: FAM-05 | C9: Corporativo y administrativo especializado | D9: 1 | E9: 0 | F9: =IFERROR(E9/D9,0) -> 0 | G9: 350 | H9: =IFERROR(K9/E9,0) -> 0 | I9: =IFERROR(H9/G9-1,0) -> -1 | J9: 350 | K9: 0 | L9: =IFERROR(K9/J9,0) -> 0 | M9: 0.88 | N9: 0 | O9: =K9-N9 -> 0 | P9: 308 | Q9: =IFERROR(O9/P9,0) -> 0 | R9: =IFERROR(J9/SUM($J$5:$J$10)*SUM('07_Gastos_Fijos'!$D$5:$D$9),0) -> 256.25 | S9: 0 | T9: =O9-R9-S9 -> -256.25 | U9: =IFERROR(T9/K9,0) -> 0 | V9: =IF(L9>=1,"VERDE",IF(L9>=0.85,"AMARILLO","ROJO")) -> ROJO
A10: Julio | B10: FAM-06 | C10: Migración, relocalización y servicios internacionales | D10: 0 | E10: 0 | F10: =IFERROR(E10/D10,0) -> 0 | G10: 500 | H10: =IFERROR(K10/E10,0) -> 0 | I10: =IFERROR(H10/G10-1,0) -> -1 | J10: 0 | K10: 0 | L10: =IFERROR(K10/J10,0) -> 0 | M10: 0.82 | N10: 0 | O10: =K10-N10 -> 0 | P10: 0 | Q10: =IFERROR(O10/P10,0) -> 0 | R10: =IFERROR(J10/SUM($J$5:$J$10)*SUM('07_Gastos_Fijos'!$D$5:$D$9),0) -> 0 | S10: 0 | T10: =O10-R10-S10 -> 0 | U10: =IFERROR(T10/K10,0) -> 0 | V10: =IF(L10>=1,"VERDE",IF(L10>=0.85,"AMARILLO","ROJO")) -> ROJO
A11: Agosto | B11: FAM-01 | C11: Notariales rápidos | D11: 10 | E11: 0 | F11: =IFERROR(E11/D11,0) -> 0 | G11: 35 | H11: =IFERROR(K11/E11,0) -> 0 | I11: =IFERROR(H11/G11-1,0) -> -1 | J11: 350 | K11: 0 | L11: =IFERROR(K11/J11,0) -> 0 | M11: 0.85 | N11: 0 | O11: =K11-N11 -> 0 | P11: 297.5 | Q11: =IFERROR(O11/P11,0) -> 0 | R11: =IFERROR(J11/SUM($J$11:$J$16)*SUM('07_Gastos_Fijos'!$D$5:$D$9),0) -> 184.40421 | S11: 0 | T11: =O11-R11-S11 -> -184.40421 | U11: =IFERROR(T11/K11,0) -> 0 | V11: =IF(L11>=1,"VERDE",IF(L11>=0.85,"AMARILLO","ROJO")) -> ROJO
A12: Agosto | B12: FAM-02 | C12: Asesorías, contratos y gestiones | D12: 8 | E12: 0 | F12: =IFERROR(E12/D12,0) -> 0 | G12: 85 | H12: =IFERROR(K12/E12,0) -> 0 | I12: =IFERROR(H12/G12-1,0) -> -1 | J12: 680 | K12: 0 | L12: =IFERROR(K12/J12,0) -> 0 | M12: 0.9 | N12: 0 | O12: =K12-N12 -> 0 | P12: 612 | Q12: =IFERROR(O12/P12,0) -> 0 | R12: =IFERROR(J12/SUM($J$11:$J$16)*SUM('07_Gastos_Fijos'!$D$5:$D$9),0) -> 358.27103 | S12: 0 | T12: =O12-R12-S12 -> -358.27103 | U12: =IFERROR(T12/K12,0) -> 0 | V12: =IF(L12>=1,"VERDE",IF(L12>=0.85,"AMARILLO","ROJO")) -> ROJO
A13: Agosto | B13: FAM-03 | C13: Inmobiliario y registral | D13: 3 | E13: 0 | F13: =IFERROR(E13/D13,0) -> 0 | G13: 300 | H13: =IFERROR(K13/E13,0) -> 0 | I13: =IFERROR(H13/G13-1,0) -> -1 | J13: 900 | K13: 0 | L13: =IFERROR(K13/J13,0) -> 0 | M13: 0.88 | N13: 0 | O13: =K13-N13 -> 0 | P13: 792 | Q13: =IFERROR(O13/P13,0) -> 0 | R13: =IFERROR(J13/SUM($J$11:$J$16)*SUM('07_Gastos_Fijos'!$D$5:$D$9),0) -> 474.18224 | S13: 0 | T13: =O13-R13-S13 -> -474.18224 | U13: =IFERROR(T13/K13,0) -> 0 | V13: =IF(L13>=1,"VERDE",IF(L13>=0.85,"AMARILLO","ROJO")) -> ROJO
A14: Agosto | B14: FAM-04 | C14: Herencias y planificación patrimonial | D14: 2 | E14: 0 | F14: =IFERROR(E14/D14,0) -> 0 | G14: 750 | H14: =IFERROR(K14/E14,0) -> 0 | I14: =IFERROR(H14/G14-1,0) -> -1 | J14: 1500 | K14: 0 | L14: =IFERROR(K14/J14,0) -> 0 | M14: 0.82 | N14: 0 | O14: =K14-N14 -> 0 | P14: 1230 | Q14: =IFERROR(O14/P14,0) -> 0 | R14: =IFERROR(J14/SUM($J$11:$J$16)*SUM('07_Gastos_Fijos'!$D$5:$D$9),0) -> 790.30374 | S14: 0 | T14: =O14-R14-S14 -> -790.30374 | U14: =IFERROR(T14/K14,0) -> 0 | V14: =IF(L14>=1,"VERDE",IF(L14>=0.85,"AMARILLO","ROJO")) -> ROJO
A15: Agosto | B15: FAM-05 | C15: Corporativo y administrativo especializado | D15: 1 | E15: 0 | F15: =IFERROR(E15/D15,0) -> 0 | G15: 350 | H15: =IFERROR(K15/E15,0) -> 0 | I15: =IFERROR(H15/G15-1,0) -> -1 | J15: 350 | K15: 0 | L15: =IFERROR(K15/J15,0) -> 0 | M15: 0.88 | N15: 0 | O15: =K15-N15 -> 0 | P15: 308 | Q15: =IFERROR(O15/P15,0) -> 0 | R15: =IFERROR(J15/SUM($J$11:$J$16)*SUM('07_Gastos_Fijos'!$D$5:$D$9),0) -> 184.40421 | S15: 0 | T15: =O15-R15-S15 -> -184.40421 | U15: =IFERROR(T15/K15,0) -> 0 | V15: =IF(L15>=1,"VERDE",IF(L15>=0.85,"AMARILLO","ROJO")) -> ROJO
A16: Agosto | B16: FAM-06 | C16: Migración, relocalización y servicios internacionales | D16: 1 | E16: 0 | F16: =IFERROR(E16/D16,0) -> 0 | G16: 500 | H16: =IFERROR(K16/E16,0) -> 0 | I16: =IFERROR(H16/G16-1,0) -> -1 | J16: 500 | K16: 0 | L16: =IFERROR(K16/J16,0) -> 0 | M16: 0.82 | N16: 0 | O16: =K16-N16 -> 0 | P16: 410 | Q16: =IFERROR(O16/P16,0) -> 0 | R16: =IFERROR(J16/SUM($J$11:$J$16)*SUM('07_Gastos_Fijos'!$D$5:$D$9),0) -> 263.43458 | S16: 0 | T16: =O16-R16-S16 -> -263.43458 | U16: =IFERROR(T16/K16,0) -> 0 | V16: =IF(L16>=1,"VERDE",IF(L16>=0.85,"AMARILLO","ROJO")) -> ROJO
A17: Septiembre | B17: FAM-01 | C17: Notariales rápidos | D17: 11 | E17: 0 | F17: =IFERROR(E17/D17,0) -> 0 | G17: 35 | H17: =IFERROR(K17/E17,0) -> 0 | I17: =IFERROR(H17/G17-1,0) -> -1 | J17: 385 | K17: 0 | L17: =IFERROR(K17/J17,0) -> 0 | M17: 0.85 | N17: 0 | O17: =K17-N17 -> 0 | P17: 327.25 | Q17: =IFERROR(O17/P17,0) -> 0 | R17: =IFERROR(J17/SUM($J$17:$J$22)*SUM('07_Gastos_Fijos'!$D$5:$D$9),0) -> 237.85616 | S17: 0 | T17: =O17-R17-S17 -> -237.85616 | U17: =IFERROR(T17/K17,0) -> 0 | V17: =IF(L17>=1,"VERDE",IF(L17>=0.85,"AMARILLO","ROJO")) -> ROJO
A18: Septiembre | B18: FAM-02 | C18: Asesorías, contratos y gestiones | D18: 9 | E18: 0 | F18: =IFERROR(E18/D18,0) -> 0 | G18: 85 | H18: =IFERROR(K18/E18,0) -> 0 | I18: =IFERROR(H18/G18-1,0) -> -1 | J18: 765 | K18: 0 | L18: =IFERROR(K18/J18,0) -> 0 | M18: 0.9 | N18: 0 | O18: =K18-N18 -> 0 | P18: 688.5 | Q18: =IFERROR(O18/P18,0) -> 0 | R18: =IFERROR(J18/SUM($J$17:$J$22)*SUM('07_Gastos_Fijos'!$D$5:$D$9),0) -> 472.62329 | S18: 0 | T18: =O18-R18-S18 -> -472.62329 | U18: =IFERROR(T18/K18,0) -> 0 | V18: =IF(L18>=1,"VERDE",IF(L18>=0.85,"AMARILLO","ROJO")) -> ROJO
A19: Septiembre | B19: FAM-03 | C19: Inmobiliario y registral | D19: 3 | E19: 0 | F19: =IFERROR(E19/D19,0) -> 0 | G19: 300 | H19: =IFERROR(K19/E19,0) -> 0 | I19: =IFERROR(H19/G19-1,0) -> -1 | J19: 900 | K19: 0 | L19: =IFERROR(K19/J19,0) -> 0 | M19: 0.88 | N19: 0 | O19: =K19-N19 -> 0 | P19: 792 | Q19: =IFERROR(O19/P19,0) -> 0 | R19: =IFERROR(J19/SUM($J$17:$J$22)*SUM('07_Gastos_Fijos'!$D$5:$D$9),0) -> 556.0274 | S19: 0 | T19: =O19-R19-S19 -> -556.0274 | U19: =IFERROR(T19/K19,0) -> 0 | V19: =IF(L19>=1,"VERDE",IF(L19>=0.85,"AMARILLO","ROJO")) -> ROJO
A20: Septiembre | B20: FAM-04 | C20: Herencias y planificación patrimonial | D20: 1 | E20: 0 | F20: =IFERROR(E20/D20,0) -> 0 | G20: 750 | H20: =IFERROR(K20/E20,0) -> 0 | I20: =IFERROR(H20/G20-1,0) -> -1 | J20: 750 | K20: 0 | L20: =IFERROR(K20/J20,0) -> 0 | M20: 0.82 | N20: 0 | O20: =K20-N20 -> 0 | P20: 615 | Q20: =IFERROR(O20/P20,0) -> 0 | R20: =IFERROR(J20/SUM($J$17:$J$22)*SUM('07_Gastos_Fijos'!$D$5:$D$9),0) -> 463.35616 | S20: 0 | T20: =O20-R20-S20 -> -463.35616 | U20: =IFERROR(T20/K20,0) -> 0 | V20: =IF(L20>=1,"VERDE",IF(L20>=0.85,"AMARILLO","ROJO")) -> ROJO
A21: Septiembre | B21: FAM-05 | C21: Corporativo y administrativo especializado | D21: 1 | E21: 0 | F21: =IFERROR(E21/D21,0) -> 0 | G21: 350 | H21: =IFERROR(K21/E21,0) -> 0 | I21: =IFERROR(H21/G21-1,0) -> -1 | J21: 350 | K21: 0 | L21: =IFERROR(K21/J21,0) -> 0 | M21: 0.88 | N21: 0 | O21: =K21-N21 -> 0 | P21: 308 | Q21: =IFERROR(O21/P21,0) -> 0 | R21: =IFERROR(J21/SUM($J$17:$J$22)*SUM('07_Gastos_Fijos'!$D$5:$D$9),0) -> 216.23288 | S21: 0 | T21: =O21-R21-S21 -> -216.23288 | U21: =IFERROR(T21/K21,0) -> 0 | V21: =IF(L21>=1,"VERDE",IF(L21>=0.85,"AMARILLO","ROJO")) -> ROJO
A22: Septiembre | B22: FAM-06 | C22: Migración, relocalización y servicios internacionales | D22: 1 | E22: 0 | F22: =IFERROR(E22/D22,0) -> 0 | G22: 500 | H22: =IFERROR(K22/E22,0) -> 0 | I22: =IFERROR(H22/G22-1,0) -> -1 | J22: 500 | K22: 0 | L22: =IFERROR(K22/J22,0) -> 0 | M22: 0.82 | N22: 0 | O22: =K22-N22 -> 0 | P22: 410 | Q22: =IFERROR(O22/P22,0) -> 0 | R22: =IFERROR(J22/SUM($J$17:$J$22)*SUM('07_Gastos_Fijos'!$D$5:$D$9),0) -> 308.90411 | S22: 0 | T22: =O22-R22-S22 -> -308.90411 | U22: =IFERROR(T22/K22,0) -> 0 | V22: =IF(L22>=1,"VERDE",IF(L22>=0.85,"AMARILLO","ROJO")) -> ROJO
A23: Octubre | B23: FAM-01 | C23: Notariales rápidos | D23: 12 | E23: 0 | F23: =IFERROR(E23/D23,0) -> 0 | G23: 35 | H23: =IFERROR(K23/E23,0) -> 0 | I23: =IFERROR(H23/G23-1,0) -> -1 | J23: 420 | K23: 0 | L23: =IFERROR(K23/J23,0) -> 0 | M23: 0.85 | N23: 0 | O23: =K23-N23 -> 0 | P23: 357 | Q23: =IFERROR(O23/P23,0) -> 0 | R23: =IFERROR(J23/SUM($J$23:$J$28)*SUM('07_Gastos_Fijos'!$D$5:$D$9),0) -> 257.01493 | S23: 0 | T23: =O23-R23-S23 -> -257.01493 | U23: =IFERROR(T23/K23,0) -> 0 | V23: =IF(L23>=1,"VERDE",IF(L23>=0.85,"AMARILLO","ROJO")) -> ROJO
A24: Octubre | B24: FAM-02 | C24: Asesorías, contratos y gestiones | D24: 9 | E24: 0 | F24: =IFERROR(E24/D24,0) -> 0 | G24: 85 | H24: =IFERROR(K24/E24,0) -> 0 | I24: =IFERROR(H24/G24-1,0) -> -1 | J24: 765 | K24: 0 | L24: =IFERROR(K24/J24,0) -> 0 | M24: 0.9 | N24: 0 | O24: =K24-N24 -> 0 | P24: 688.5 | Q24: =IFERROR(O24/P24,0) -> 0 | R24: =IFERROR(J24/SUM($J$23:$J$28)*SUM('07_Gastos_Fijos'!$D$5:$D$9),0) -> 468.13433 | S24: 0 | T24: =O24-R24-S24 -> -468.13433 | U24: =IFERROR(T24/K24,0) -> 0 | V24: =IF(L24>=1,"VERDE",IF(L24>=0.85,"AMARILLO","ROJO")) -> ROJO
A25: Octubre | B25: FAM-03 | C25: Inmobiliario y registral | D25: 3 | E25: 0 | F25: =IFERROR(E25/D25,0) -> 0 | G25: 300 | H25: =IFERROR(K25/E25,0) -> 0 | I25: =IFERROR(H25/G25-1,0) -> -1 | J25: 900 | K25: 0 | L25: =IFERROR(K25/J25,0) -> 0 | M25: 0.88 | N25: 0 | O25: =K25-N25 -> 0 | P25: 792 | Q25: =IFERROR(O25/P25,0) -> 0 | R25: =IFERROR(J25/SUM($J$23:$J$28)*SUM('07_Gastos_Fijos'!$D$5:$D$9),0) -> 550.74627 | S25: 0 | T25: =O25-R25-S25 -> -550.74627 | U25: =IFERROR(T25/K25,0) -> 0 | V25: =IF(L25>=1,"VERDE",IF(L25>=0.85,"AMARILLO","ROJO")) -> ROJO
A26: Octubre | B26: FAM-04 | C26: Herencias y planificación patrimonial | D26: 1 | E26: 0 | F26: =IFERROR(E26/D26,0) -> 0 | G26: 750 | H26: =IFERROR(K26/E26,0) -> 0 | I26: =IFERROR(H26/G26-1,0) -> -1 | J26: 750 | K26: 0 | L26: =IFERROR(K26/J26,0) -> 0 | M26: 0.82 | N26: 0 | O26: =K26-N26 -> 0 | P26: 615 | Q26: =IFERROR(O26/P26,0) -> 0 | R26: =IFERROR(J26/SUM($J$23:$J$28)*SUM('07_Gastos_Fijos'!$D$5:$D$9),0) -> 458.95522 | S26: 0 | T26: =O26-R26-S26 -> -458.95522 | U26: =IFERROR(T26/K26,0) -> 0 | V26: =IF(L26>=1,"VERDE",IF(L26>=0.85,"AMARILLO","ROJO")) -> ROJO
A27: Octubre | B27: FAM-05 | C27: Corporativo y administrativo especializado | D27: 1 | E27: 0 | F27: =IFERROR(E27/D27,0) -> 0 | G27: 350 | H27: =IFERROR(K27/E27,0) -> 0 | I27: =IFERROR(H27/G27-1,0) -> -1 | J27: 350 | K27: 0 | L27: =IFERROR(K27/J27,0) -> 0 | M27: 0.88 | N27: 0 | O27: =K27-N27 -> 0 | P27: 308 | Q27: =IFERROR(O27/P27,0) -> 0 | R27: =IFERROR(J27/SUM($J$23:$J$28)*SUM('07_Gastos_Fijos'!$D$5:$D$9),0) -> 214.1791 | S27: 0 | T27: =O27-R27-S27 -> -214.1791 | U27: =IFERROR(T27/K27,0) -> 0 | V27: =IF(L27>=1,"VERDE",IF(L27>=0.85,"AMARILLO","ROJO")) -> ROJO
A28: Octubre | B28: FAM-06 | C28: Migración, relocalización y servicios internacionales | D28: 1 | E28: 0 | F28: =IFERROR(E28/D28,0) -> 0 | G28: 500 | H28: =IFERROR(K28/E28,0) -> 0 | I28: =IFERROR(H28/G28-1,0) -> -1 | J28: 500 | K28: 0 | L28: =IFERROR(K28/J28,0) -> 0 | M28: 0.82 | N28: 0 | O28: =K28-N28 -> 0 | P28: 410 | Q28: =IFERROR(O28/P28,0) -> 0 | R28: =IFERROR(J28/SUM($J$23:$J$28)*SUM('07_Gastos_Fijos'!$D$5:$D$9),0) -> 305.97015 | S28: 0 | T28: =O28-R28-S28 -> -305.97015 | U28: =IFERROR(T28/K28,0) -> 0 | V28: =IF(L28>=1,"VERDE",IF(L28>=0.85,"AMARILLO","ROJO")) -> ROJO
A29: Noviembre | B29: FAM-01 | C29: Notariales rápidos | D29: 13 | E29: 0 | F29: =IFERROR(E29/D29,0) -> 0 | G29: 35 | H29: =IFERROR(K29/E29,0) -> 0 | I29: =IFERROR(H29/G29-1,0) -> -1 | J29: 455 | K29: 0 | L29: =IFERROR(K29/J29,0) -> 0 | M29: 0.85 | N29: 0 | O29: =K29-N29 -> 0 | P29: 386.75 | Q29: =IFERROR(O29/P29,0) -> 0 | R29: =IFERROR(J29/SUM($J$29:$J$34)*SUM('07_Gastos_Fijos'!$D$5:$D$9),0) -> 269.65177 | S29: 0 | T29: =O29-R29-S29 -> -269.65177 | U29: =IFERROR(T29/K29,0) -> 0 | V29: =IF(L29>=1,"VERDE",IF(L29>=0.85,"AMARILLO","ROJO")) -> ROJO
A30: Noviembre | B30: FAM-02 | C30: Asesorías, contratos y gestiones | D30: 10 | E30: 0 | F30: =IFERROR(E30/D30,0) -> 0 | G30: 85 | H30: =IFERROR(K30/E30,0) -> 0 | I30: =IFERROR(H30/G30-1,0) -> -1 | J30: 850 | K30: 0 | L30: =IFERROR(K30/J30,0) -> 0 | M30: 0.9 | N30: 0 | O30: =K30-N30 -> 0 | P30: 765 | Q30: =IFERROR(O30/P30,0) -> 0 | R30: =IFERROR(J30/SUM($J$29:$J$34)*SUM('07_Gastos_Fijos'!$D$5:$D$9),0) -> 503.74507 | S30: 0 | T30: =O30-R30-S30 -> -503.74507 | U30: =IFERROR(T30/K30,0) -> 0 | V30: =IF(L30>=1,"VERDE",IF(L30>=0.85,"AMARILLO","ROJO")) -> ROJO
A31: Noviembre | B31: FAM-03 | C31: Inmobiliario y registral | D31: 3 | E31: 0 | F31: =IFERROR(E31/D31,0) -> 0 | G31: 300 | H31: =IFERROR(K31/E31,0) -> 0 | I31: =IFERROR(H31/G31-1,0) -> -1 | J31: 900 | K31: 0 | L31: =IFERROR(K31/J31,0) -> 0 | M31: 0.88 | N31: 0 | O31: =K31-N31 -> 0 | P31: 792 | Q31: =IFERROR(O31/P31,0) -> 0 | R31: =IFERROR(J31/SUM($J$29:$J$34)*SUM('07_Gastos_Fijos'!$D$5:$D$9),0) -> 533.37714 | S31: 0 | T31: =O31-R31-S31 -> -533.37714 | U31: =IFERROR(T31/K31,0) -> 0 | V31: =IF(L31>=1,"VERDE",IF(L31>=0.85,"AMARILLO","ROJO")) -> ROJO
A32: Noviembre | B32: FAM-04 | C32: Herencias y planificación patrimonial | D32: 1 | E32: 0 | F32: =IFERROR(E32/D32,0) -> 0 | G32: 750 | H32: =IFERROR(K32/E32,0) -> 0 | I32: =IFERROR(H32/G32-1,0) -> -1 | J32: 750 | K32: 0 | L32: =IFERROR(K32/J32,0) -> 0 | M32: 0.82 | N32: 0 | O32: =K32-N32 -> 0 | P32: 615 | Q32: =IFERROR(O32/P32,0) -> 0 | R32: =IFERROR(J32/SUM($J$29:$J$34)*SUM('07_Gastos_Fijos'!$D$5:$D$9),0) -> 444.48095 | S32: 0 | T32: =O32-R32-S32 -> -444.48095 | U32: =IFERROR(T32/K32,0) -> 0 | V32: =IF(L32>=1,"VERDE",IF(L32>=0.85,"AMARILLO","ROJO")) -> ROJO
A33: Noviembre | B33: FAM-05 | C33: Corporativo y administrativo especializado | D33: 1 | E33: 0 | F33: =IFERROR(E33/D33,0) -> 0 | G33: 350 | H33: =IFERROR(K33/E33,0) -> 0 | I33: =IFERROR(H33/G33-1,0) -> -1 | J33: 350 | K33: 0 | L33: =IFERROR(K33/J33,0) -> 0 | M33: 0.88 | N33: 0 | O33: =K33-N33 -> 0 | P33: 308 | Q33: =IFERROR(O33/P33,0) -> 0 | R33: =IFERROR(J33/SUM($J$29:$J$34)*SUM('07_Gastos_Fijos'!$D$5:$D$9),0) -> 207.42444 | S33: 0 | T33: =O33-R33-S33 -> -207.42444 | U33: =IFERROR(T33/K33,0) -> 0 | V33: =IF(L33>=1,"VERDE",IF(L33>=0.85,"AMARILLO","ROJO")) -> ROJO
A34: Noviembre | B34: FAM-06 | C34: Migración, relocalización y servicios internacionales | D34: 1 | E34: 0 | F34: =IFERROR(E34/D34,0) -> 0 | G34: 500 | H34: =IFERROR(K34/E34,0) -> 0 | I34: =IFERROR(H34/G34-1,0) -> -1 | J34: 500 | K34: 0 | L34: =IFERROR(K34/J34,0) -> 0 | M34: 0.82 | N34: 0 | O34: =K34-N34 -> 0 | P34: 410 | Q34: =IFERROR(O34/P34,0) -> 0 | R34: =IFERROR(J34/SUM($J$29:$J$34)*SUM('07_Gastos_Fijos'!$D$5:$D$9),0) -> 296.32063 | S34: 0 | T34: =O34-R34-S34 -> -296.32063 | U34: =IFERROR(T34/K34,0) -> 0 | V34: =IF(L34>=1,"VERDE",IF(L34>=0.85,"AMARILLO","ROJO")) -> ROJO
A35: Diciembre | B35: FAM-01 | C35: Notariales rápidos | D35: 14 | E35: 0 | F35: =IFERROR(E35/D35,0) -> 0 | G35: 35 | H35: =IFERROR(K35/E35,0) -> 0 | I35: =IFERROR(H35/G35-1,0) -> -1 | J35: 490 | K35: 0 | L35: =IFERROR(K35/J35,0) -> 0 | M35: 0.85 | N35: 0 | O35: =K35-N35 -> 0 | P35: 416.5 | Q35: =IFERROR(O35/P35,0) -> 0 | R35: =IFERROR(J35/SUM($J$35:$J$40)*SUM('07_Gastos_Fijos'!$D$5:$D$9),0) -> 266.89614 | S35: 0 | T35: =O35-R35-S35 -> -266.89614 | U35: =IFERROR(T35/K35,0) -> 0 | V35: =IF(L35>=1,"VERDE",IF(L35>=0.85,"AMARILLO","ROJO")) -> ROJO
A36: Diciembre | B36: FAM-02 | C36: Asesorías, contratos y gestiones | D36: 10 | E36: 0 | F36: =IFERROR(E36/D36,0) -> 0 | G36: 85 | H36: =IFERROR(K36/E36,0) -> 0 | I36: =IFERROR(H36/G36-1,0) -> -1 | J36: 850 | K36: 0 | L36: =IFERROR(K36/J36,0) -> 0 | M36: 0.9 | N36: 0 | O36: =K36-N36 -> 0 | P36: 765 | Q36: =IFERROR(O36/P36,0) -> 0 | R36: =IFERROR(J36/SUM($J$35:$J$40)*SUM('07_Gastos_Fijos'!$D$5:$D$9),0) -> 462.98309 | S36: 0 | T36: =O36-R36-S36 -> -462.98309 | U36: =IFERROR(T36/K36,0) -> 0 | V36: =IF(L36>=1,"VERDE",IF(L36>=0.85,"AMARILLO","ROJO")) -> ROJO
A37: Diciembre | B37: FAM-03 | C37: Inmobiliario y registral | D37: 4 | E37: 0 | F37: =IFERROR(E37/D37,0) -> 0 | G37: 300 | H37: =IFERROR(K37/E37,0) -> 0 | I37: =IFERROR(H37/G37-1,0) -> -1 | J37: 1200 | K37: 0 | L37: =IFERROR(K37/J37,0) -> 0 | M37: 0.88 | N37: 0 | O37: =K37-N37 -> 0 | P37: 1056 | Q37: =IFERROR(O37/P37,0) -> 0 | R37: =IFERROR(J37/SUM($J$35:$J$40)*SUM('07_Gastos_Fijos'!$D$5:$D$9),0) -> 653.62319 | S37: 0 | T37: =O37-R37-S37 -> -653.62319 | U37: =IFERROR(T37/K37,0) -> 0 | V37: =IF(L37>=1,"VERDE",IF(L37>=0.85,"AMARILLO","ROJO")) -> ROJO
A38: Diciembre | B38: FAM-04 | C38: Herencias y planificación patrimonial | D38: 1 | E38: 0 | F38: =IFERROR(E38/D38,0) -> 0 | G38: 750 | H38: =IFERROR(K38/E38,0) -> 0 | I38: =IFERROR(H38/G38-1,0) -> -1 | J38: 750 | K38: 0 | L38: =IFERROR(K38/J38,0) -> 0 | M38: 0.82 | N38: 0 | O38: =K38-N38 -> 0 | P38: 615 | Q38: =IFERROR(O38/P38,0) -> 0 | R38: =IFERROR(J38/SUM($J$35:$J$40)*SUM('07_Gastos_Fijos'!$D$5:$D$9),0) -> 408.51449 | S38: 0 | T38: =O38-R38-S38 -> -408.51449 | U38: =IFERROR(T38/K38,0) -> 0 | V38: =IF(L38>=1,"VERDE",IF(L38>=0.85,"AMARILLO","ROJO")) -> ROJO
A39: Diciembre | B39: FAM-05 | C39: Corporativo y administrativo especializado | D39: 1 | E39: 0 | F39: =IFERROR(E39/D39,0) -> 0 | G39: 350 | H39: =IFERROR(K39/E39,0) -> 0 | I39: =IFERROR(H39/G39-1,0) -> -1 | J39: 350 | K39: 0 | L39: =IFERROR(K39/J39,0) -> 0 | M39: 0.88 | N39: 0 | O39: =K39-N39 -> 0 | P39: 308 | Q39: =IFERROR(O39/P39,0) -> 0 | R39: =IFERROR(J39/SUM($J$35:$J$40)*SUM('07_Gastos_Fijos'!$D$5:$D$9),0) -> 190.6401 | S39: 0 | T39: =O39-R39-S39 -> -190.6401 | U39: =IFERROR(T39/K39,0) -> 0 | V39: =IF(L39>=1,"VERDE",IF(L39>=0.85,"AMARILLO","ROJO")) -> ROJO
A40: Diciembre | B40: FAM-06 | C40: Migración, relocalización y servicios internacionales | D40: 1 | E40: 0 | F40: =IFERROR(E40/D40,0) -> 0 | G40: 500 | H40: =IFERROR(K40/E40,0) -> 0 | I40: =IFERROR(H40/G40-1,0) -> -1 | J40: 500 | K40: 0 | L40: =IFERROR(K40/J40,0) -> 0 | M40: 0.82 | N40: 0 | O40: =K40-N40 -> 0 | P40: 410 | Q40: =IFERROR(O40/P40,0) -> 0 | R40: =IFERROR(J40/SUM($J$35:$J$40)*SUM('07_Gastos_Fijos'!$D$5:$D$9),0) -> 272.343 | S40: 0 | T40: =O40-R40-S40 -> -272.343 | U40: =IFERROR(T40/K40,0) -> 0 | V40: =IF(L40>=1,"VERDE",IF(L40>=0.85,"AMARILLO","ROJO")) -> ROJO
A43: Nota: La realidad parcial de julio se cargó con $350 efectivamente cobrados. Los costos directos y la comisión permanecen en cero hasta que se asignen por expediente; por ello la utilidad real es preliminar.

Sheet 04_Plan_Cuentas
A1: 04 | Plan de cuentas de ingresos y egresos
A2: Cada movimiento financiero debe registrar un código de cuenta. Los ingresos se relacionan con familias de servicios; los egresos se clasifican por naturaleza y centro de costo.
A4: Código cuenta | B4: Tipo | C4: Grupo | D4: Subgrupo | E4: Cuenta / concepto | F4: Naturaleza | G4: Código categoría relacionado | H4: Código familia relacionado | I4: Centro de costo | J4: Afecta utilidad | K4: Estado | L4: Regla de uso
A5: ING-NOT-001 | B5: Ingreso | C5: Servicios jurídicos | D5: Notariales rápidos | E5: Ingresos por servicios notariales rápidos | F5: Operativo | G5: NOT | H5: FAM-01 | I5: Operación jurídica | J5: Sí | K5: Activo | L5: Usar para actas, auténticas, declaraciones, certificaciones y autorizaciones.
A6: ING-ASE-001 | B6: Ingreso | C6: Servicios jurídicos | D6: Asesorías y gestiones | E6: Ingresos por asesorías, contratos y gestiones | F6: Operativo | G6: ADM | H6: FAM-02 | I6: Operación jurídica | J6: Sí | K6: Activo | L6: Usar para asesorías, contratos, escritos y acompañamientos.
A7: ING-RAI-001 | B7: Ingreso | C7: Servicios jurídicos | D7: Inmobiliario y registral | E7: Ingresos por servicios inmobiliarios y registrales | F7: Operativo | G7: RAI | H7: FAM-03 | I7: Operación jurídica | J7: Sí | K7: Activo | L7: Usar para compraventas, hipotecas, promesas, registros y remediciones.
A8: ING-SUC-001 | B8: Ingreso | C8: Servicios jurídicos | D8: Herencias y patrimonio | E8: Ingresos por sucesiones y planificación patrimonial | F8: Operativo | G8: SUC | H8: FAM-04 | I8: Operación jurídica | J8: Sí | K8: Activo | L8: Usar para aceptaciones de herencia, cesiones y planificación patrimonial.
A9: ING-COR-001 | B9: Ingreso | C9: Servicios jurídicos | D9: Corporativo y administrativo | E9: Ingresos por servicios corporativos y administrativos especializados | F9: Operativo | G9: COR | H9: FAM-05 | I9: Operación jurídica | J9: Sí | K9: Activo | L9: Usar para sociedades, protocolizaciones, OPAMSS, compliance y trámites especializados.
A10: ING-MIG-001 | B10: Ingreso | C10: Servicios jurídicos | D10: Migración y relocalización | E10: Ingresos por migración, relocalización y servicios internacionales | F10: Operativo | G10: MIG | H10: FAM-06 | I10: Operación jurídica | J10: Sí | K10: Activo | L10: Usar para NIT, residencias, traducciones y relocalización.
A11: ING-LIT-001 | B11: Ingreso | C11: Servicios jurídicos | D11: Litigios | E11: Ingresos por litigios y controversias | F11: Operativo | G11: LIT | H11: FAM-07 | I11: Operación jurídica | J11: Sí | K11: Activo | L11: Usar para procesos judiciales, conciliaciones y arbitrajes.
A12: ING-LAB-001 | B12: Ingreso | C12: Servicios jurídicos | D12: Laboral preventivo | E12: Ingresos por servicios laborales preventivos | F12: Operativo | G12: LAB | H12: FAM-08 | I12: Operación jurídica | J12: Sí | K12: Activo | L12: Usar para contratos, reglamentos, auditorías e inspecciones.
A13: ING-IPI-001 | B13: Ingreso | C13: Servicios jurídicos | D13: Propiedad intelectual | E13: Ingresos por propiedad intelectual | F13: Operativo | G13: IPI | H13: FAM-09 | I13: Operación jurídica | J13: Sí | K13: Activo | L13: Usar para marcas, derechos de autor, patentes y diseños.
A14: ING-DTC-001 | B14: Ingreso | C14: Servicios jurídicos | D14: Datos y cumplimiento | E14: Ingresos por protección de datos, tecnología y cumplimiento | F14: Operativo | G14: DTC | H14: FAM-10 | I14: Operación jurídica | J14: Sí | K14: Activo | L14: Usar para políticas, diagnósticos, comercio digital y compliance.
A15: ING-COB-001 | B15: Ingreso | C15: Servicios jurídicos | D15: Cobranza | E15: Ingresos por cobranza y recuperación | F15: Operativo | G15: COB | H15: FAM-11 | I15: Operación jurídica | J15: Sí | K15: Activo | L15: Usar para cobranza preventiva, extrajudicial y judicial.
A16: ING-OSF-001 | B16: Ingreso | C16: Servicios jurídicos | D16: Organizaciones sin fines de lucro | E16: Ingresos por servicios a OSFL | F16: Operativo | G16: OSF | H16: FAM-12 | I16: Operación jurídica | J16: Sí | K16: Activo | L16: Usar para constitución, gobierno y cumplimiento de asociaciones y fundaciones.
A17: ING-OTR-001 | B17: Ingreso | C17: Otros ingresos | D17: No jurídicos | E17: Otros ingresos operativos | F17: Otros | I17: Administración | J17: Sí | K17: Activo | L17: Usar solo cuando el ingreso no corresponde a un servicio jurídico codificado.
A18: EGR-PER-001 | B18: Egreso | C18: Personal | D18: Salarios | E18: Salario Guadalupe Sánchez | F18: Fijo | I18: Operación jurídica | J18: Sí | K18: Activo | L18: Pago mensual.
A19: EGR-PER-002 | B19: Egreso | C19: Personal | D19: Salarios | E19: Salario Alfredo Gallegos | F19: Fijo | I19: Operación jurídica | J19: Sí | K19: Activo | L19: Pago mensual.
A20: EGR-PER-003 | B20: Egreso | C20: Personal | D20: Salarios | E20: Salario Andrea Escobar | F20: Fijo | I20: Comercial y administración | J20: Sí | K20: Activo | L20: Pago mensual.
A21: EGR-PER-004 | B21: Egreso | C21: Personal | D21: Variable | E21: Comisión Andrea | F21: Variable | I21: Comercial | J21: Sí | K21: Activo | L21: Según utilidad directa cobrada y reglas COM-001 a COM-004.
A22: EGR-LOC-001 | B22: Egreso | C22: Local | D22: Arrendamiento | E22: Arrendamiento de oficina | F22: Fijo | I22: Administración | J22: Sí | K22: Activo | L22: Pago mensual de local.
A23: EGR-SER-001 | B23: Egreso | C23: Servicios básicos | D23: Internet | E23: Internet y telefonía | F23: Fijo | I23: Administración | J23: Sí | K23: Activo | L23: Pago mensual.
A24: EGR-SER-002 | B24: Egreso | C24: Servicios básicos | D24: Energía | E24: Energía eléctrica | F24: Variable | I24: Administración | J24: Sí | K24: Activo | L24: Registrar factura mensual.
A25: EGR-SER-003 | B25: Egreso | C25: Servicios básicos | D25: Agua | E25: Agua y consumo | F25: Variable | I25: Administración | J25: Sí | K25: Activo | L25: Registrar factura o compra.
A26: EGR-ADM-001 | B26: Egreso | C26: Administración | D26: Papelería | E26: Papelería e insumos | F26: Variable | I26: Administración | J26: Sí | K26: Activo | L26: Papel, tinta, copias e insumos.
A27: EGR-ADM-002 | B27: Egreso | C27: Administración | D27: Mantenimiento | E27: Mantenimiento y reparaciones | F27: Variable | I27: Administración | J27: Sí | K27: Activo | L27: Mantenimiento de oficina y equipo.
A28: EGR-ADM-003 | B28: Egreso | C28: Administración | D28: Capacitación | E28: Capacitación y formación | F28: Variable | I28: Administración | J28: Sí | K28: Activo | L28: Cursos y formación del equipo.
... A39: EGR-OTR-001 | B39: Egreso | C39: Otros | D39: Otros egresos | E39: Otros egresos operativos | F39: Variable | I39: Administración | J39: Sí | K39: Activo | L39: Usar solo cuando no exista una cuenta específica.
A40: ING-PEN-001 | B40: Ingreso | C40: Servicios jurídicos | D40: Derecho Penal | E40: Ingresos por servicios de Derecho Penal | F40: Operativo | G40: PEN | H40: FAM-13 | I40: Operación jurídica | J40: Sí | K40: Activo | L40: Usar para defensa penal, representación de víctimas, actuaciones ante FGR, delitos económicos y ejecución penal.

Sheet 16_Movimientos_Codificados
A1: 16 | Plantilla de ingresos y egresos codificados
A2: Esta es la estructura que debe usar el sistema y, temporalmente, el control manual. Cada movimiento debe tener código de cuenta; los ingresos jurídicos también deben tener código de servicio.
A4: ID movimiento | B4: Fecha | C4: Mes | D4: Tipo | E4: Código cuenta | F4: Cuenta | G4: Cliente / proveedor | H4: ID expediente | I4: Código servicio | J4: Servicio | K4: Categoría | L4: Subcategoría | M4: Monto bruto ($) | N4: IVA / impuestos ($) | O4: Reembolsable / tercero ($) | P4: Monto neto operativo ($) | Q4: Estado | R4: Observaciones
A5: MOV-2026-0001 | B5: 46218 | C5: Julio | D5: Ingreso | E5: ING-SUC-001 | F5: Ingresos por sucesiones y planificación patrimonial | G5: David Juárez | H5: EXP-2026-001 | I5: AGL-NOT-PAT-002 | J5: Aceptación de herencia notarial | K5: NOT | L5: PAT | M5: 200 | N5: 0 | O5: 0 | P5: 200 | Q5: Cobrado | R5: Adelanto de honorarios; saldo pendiente $1,300.
A6: MOV-2026-0002 | B6: 46221 | C6: Julio | D6: Egreso | E6: EGR-PUB-001 | F6: Publicaciones y edictos | G6: La Prensa Gráfica | H6: EXP-2026-002 | I6: AGL-NOT-PAT-002 | J6: Aceptación de herencia notarial | K6: NOT | L6: PAT | M6: 23.75 | N6: 0 | O6: 23.75 | P6: 0 | Q6: Pagado | R6: Costo reembolsable o atribuible al expediente.
A7: MOV-2026-0003 | B7: 46234 | C7: Julio | D7: Egreso | E7: EGR-PER-003 | F7: Salario Andrea Escobar | G7: Andrea Escobar | M7: 250 | N7: 0 | O7: 0 | P7: 250 | Q7: Pagado | R7: Salario fijo mensual.

Sheet 17_Resumen_Mensual
A1: 17 | Resumen mensual de metas y resultados
A2: Consolida las metas por familia y permite medir ingresos, utilidad, margen y cumplimiento real de julio a diciembre.
A4: Mes | B4: Meta ingresos ($) | C4: Ingresos reales ($) | D4: Cumplimiento ingresos % | E4: Meta utilidad directa ($) | F4: Utilidad directa real ($) | G4: Cumplimiento utilidad directa % | H4: Gastos fijos ($) | I4: Comisión Andrea ($) | J4: Utilidad operativa real ($) | K4: Utilidad operativa mínima ($) | L4: Margen operativo real % | M4: Margen operativo mínimo % | N4: Brecha utilidad mínima ($) | O4: Semáforo general | Q4: Mes | R4: Utilidad operativa real | S4: Utilidad mínima
A5: Julio | B5: =SUM('15_Cumplimiento_Metas'!J5:J10) -> 3080 | C5: =SUM('15_Cumplimiento_Metas'!K5:K10) -> 350 | D5: =IFERROR(C5/B5,0) -> 0.11363636 | E5: =SUM('15_Cumplimiento_Metas'!P5:P10) -> 2668 | F5: =SUM('15_Cumplimiento_Metas'!O5:O10) -> 350 | G5: =IFERROR(F5/E5,0) -> 0.13118441 | H5: =SUM('07_Gastos_Fijos'!$D$5:$D$9) -> 2255 | I5: =SUM('15_Cumplimiento_Metas'!S5:S10) -> 0 | J5: =F5-H5-I5 -> -1905 | K5: =B5*'07_Gastos_Fijos'!$B$13 -> 616 | L5: =IFERROR(J5/C5,0) -> -5.4428571 | M5: ='07_Gastos_Fijos'!$B$13 -> 0.2 | N5: =J5-K5 -> -2521 | O5: =IF(J5>=K5,"VERDE",IF(J5>=0,"AMARILLO","ROJO")) -> ROJO | Q5: Julio | R5: =J5 -> -1905 | S5: =K5 -> 616
A6: Agosto | B6: =SUM('15_Cumplimiento_Metas'!J11:J16) -> 4280 | C6: =SUM('15_Cumplimiento_Metas'!K11:K16) -> 0 | D6: =IFERROR(C6/B6,0) -> 0 | E6: =SUM('15_Cumplimiento_Metas'!P11:P16) -> 3649.5 | F6: =SUM('15_Cumplimiento_Metas'!O11:O16) -> 0 | G6: =IFERROR(F6/E6,0) -> 0 | H6: =SUM('07_Gastos_Fijos'!$D$5:$D$9) -> 2255 | I6: =SUM('15_Cumplimiento_Metas'!S11:S16) -> 0 | J6: =F6-H6-I6 -> -2255 | K6: =B6*'07_Gastos_Fijos'!$B$13 -> 856 | L6: =IFERROR(J6/C6,0) -> 0 | M6: ='07_Gastos_Fijos'!$B$13 -> 0.2 | N6: =J6-K6 -> -3111 | O6: =IF(J6>=K6,"VERDE",IF(J6>=0,"AMARILLO","ROJO")) -> ROJO | Q6: Agosto | R6: =J6 -> -2255 | S6: =K6 -> 856
A7: Septiembre | B7: =SUM('15_Cumplimiento_Metas'!J17:J22) -> 3650 | C7: =SUM('15_Cumplimiento_Metas'!K17:K22) -> 0 | D7: =IFERROR(C7/B7,0) -> 0 | E7: =SUM('15_Cumplimiento_Metas'!P17:P22) -> 3140.75 | F7: =SUM('15_Cumplimiento_Metas'!O17:O22) -> 0 | G7: =IFERROR(F7/E7,0) -> 0 | H7: =SUM('07_Gastos_Fijos'!$D$5:$D$9) -> 2255 | I7: =SUM('15_Cumplimiento_Metas'!S17:S22) -> 0 | J7: =F7-H7-I7 -> -2255 | K7: =B7*'07_Gastos_Fijos'!$B$13 -> 730 | L7: =IFERROR(J7/C7,0) -> 0 | M7: ='07_Gastos_Fijos'!$B$13 -> 0.2 | N7: =J7-K7 -> -2985 | O7: =IF(J7>=K7,"VERDE",IF(J7>=0,"AMARILLO","ROJO")) -> ROJO | Q7: Septiembre | R7: =J7 -> -2255 | S7: =K7 -> 730
A8: Octubre | B8: =SUM('15_Cumplimiento_Metas'!J23:J28) -> 3685 | C8: =SUM('15_Cumplimiento_Metas'!K23:K28) -> 0 | D8: =IFERROR(C8/B8,0) -> 0 | E8: =SUM('15_Cumplimiento_Metas'!P23:P28) -> 3170.5 | F8: =SUM('15_Cumplimiento_Metas'!O23:O28) -> 0 | G8: =IFERROR(F8/E8,0) -> 0 | H8: =SUM('07_Gastos_Fijos'!$D$5:$D$9) -> 2255 | I8: =SUM('15_Cumplimiento_Metas'!S23:S28) -> 0 | J8: =F8-H8-I8 -> -2255 | K8: =B8*'07_Gastos_Fijos'!$B$13 -> 737 | L8: =IFERROR(J8/C8,0) -> 0 | M8: ='07_Gastos_Fijos'!$B$13 -> 0.2 | N8: =J8-K8 -> -2992 | O8: =IF(J8>=K8,"VERDE",IF(J8>=0,"AMARILLO","ROJO")) -> ROJO | Q8: Octubre | R8: =J8 -> -2255 | S8: =K8 -> 737
A9: Noviembre | B9: =SUM('15_Cumplimiento_Metas'!J29:J34) -> 3805 | C9: =SUM('15_Cumplimiento_Metas'!K29:K34) -> 0 | D9: =IFERROR(C9/B9,0) -> 0 | E9: =SUM('15_Cumplimiento_Metas'!P29:P34) -> 3276.75 | F9: =SUM('15_Cumplimiento_Metas'!O29:O34) -> 0 | G9: =IFERROR(F9/E9,0) -> 0 | H9: =SUM('07_Gastos_Fijos'!$D$5:$D$9) -> 2255 | I9: =SUM('15_Cumplimiento_Metas'!S29:S34) -> 0 | J9: =F9-H9-I9 -> -2255 | K9: =B9*'07_Gastos_Fijos'!$B$13 -> 761 | L9: =IFERROR(J9/C9,0) -> 0 | M9: ='07_Gastos_Fijos'!$B$13 -> 0.2 | N9: =J9-K9 -> -3016 | O9: =IF(J9>=K9,"VERDE",IF(J9>=0,"AMARILLO","ROJO")) -> ROJO | Q9: Noviembre | R9: =J9 -> -2255 | S9: =K9 -> 761
A10: Diciembre | B10: =SUM('15_Cumplimiento_Metas'!J35:J40) -> 4140 | C10: =SUM('15_Cumplimiento_Metas'!K35:K40) -> 0 | D10: =IFERROR(C10/B10,0) -> 0 | E10: =SUM('15_Cumplimiento_Metas'!P35:P40) -> 3570.5 | F10: =SUM('15_Cumplimiento_Metas'!O35:O40) -> 0 | G10: =IFERROR(F10/E10,0) -> 0 | H10: =SUM('07_Gastos_Fijos'!$D$5:$D$9) -> 2255 | I10: =SUM('15_Cumplimiento_Metas'!S35:S40) -> 0 | J10: =F10-H10-I10 -> -2255 | K10: =B10*'07_Gastos_Fijos'!$B$13 -> 828 | L10: =IFERROR(J10/C10,0) -> 0 | M10: ='07_Gastos_Fijos'!$B$13 -> 0.2 | N10: =J10-K10 -> -3083 | O10: =IF(J10>=K10,"VERDE",IF(J10>=0,"AMARILLO","ROJO")) -> ROJO | Q10: Diciembre | R10: =J10 -> -2255 | S10: =K10 -> 828
A12: TOTAL / PROMEDIO | B12: =SUM(B5:B10) -> 22640 | C12: =SUM(C5:C10) -> 350 | D12: =IFERROR(C12/B12,0) -> 0.015459364 | E12: =SUM(E5:E10) -> 19476 | F12: =SUM(F5:F10) -> 350 | G12: =IFERROR(F12/E12,0) -> 0.017970836 | H12: =SUM(H5:H10) -> 13530 | I12: =SUM(I5:I10) -> 0 | J12: =SUM(J5:J10) -> -13180 | K12: =SUM(K5:K10) -> 4528 | L12: =IFERROR(J12/C12,0) -> -37.657143 | M12: =AVERAGE(M5:M10) -> 0.2 | N12: =SUM(N5:N10) -> -17708

Sheet 18_Procedimiento_Catalogo
A1: 18 | Procedimiento de alta y modificación del catálogo
A2: Procedimiento obligatorio para crear categorías, subcategorías y servicios sin duplicar códigos ni afectar el histórico.
A4: Paso | B4: Etapa | C4: Acción | D4: Aplica a | E4: Responsable solicitante | F4: Responsable aprobador | G4: Validación obligatoria | H4: Resultado esperado | I4: Estado | J4: Plazo recomendado | K4: Registro requerido | L4: Regla del código | M4: Observaciones
A5: 1 | B5: Solicitud | C5: Registrar la necesidad de una nueva categoría, subcategoría o servicio. | D5: Categoría / Subcategoría / Servicio | E5: Socio, abogado o administración | G5: Indicar nombre, alcance, motivo y servicios relacionados. | H5: Solicitud completa | I5: Solicitado | J5: 1 día | K5: Formulario de control | L5: No asignar código definitivo todavía.
A6: 2 | B6: Revisión de duplicidad | C6: Buscar por nombre, palabras clave, etiquetas y alcance. | D6: Categoría / Subcategoría / Servicio | E6: Administrador del catálogo | G6: Confirmar que no exista una clasificación o servicio equivalente. | H6: Resultado de revisión | I6: En revisión | J6: 1-2 días | K6: Evidencia de búsqueda | L6: No crear un código si ya existe una opción válida.
A7: 3 | B7: Definición de nivel | C7: Determinar si corresponde categoría, subcategoría, servicio, modalidad o etiqueta. | D7: Todos | E7: Administrador del catálogo | F7: Socio administrador | G7: Aplicar criterios definidos en esta hoja. | H7: Nivel correcto | I7: En revisión | J7: 1 día | K7: Justificación | L7: Una tarifa distinta no crea un nuevo servicio.
A8: 4 | B8: Propuesta de código | C8: Preparar código disponible según la estructura oficial. | D8: Categoría / Subcategoría / Servicio | E8: Administrador del catálogo | G8: Validar unicidad global y formato. | H8: Código propuesto | I8: En revisión | J8: 1 día | K8: Código propuesto | L8: Categoría: 3 letras; Subcategoría: 3 letras; Servicio: AGL-CAT-SUB-000.
A9: 5 | B9: Aprobación | C9: Autorizar o rechazar la creación. | D9: Todos | E9: Administrador del catálogo | F9: Socio administrador | G9: Revisar impacto comercial, operativo y de reportes. | H9: Decisión formal | I9: Aprobado / Rechazado | J9: 2 días | K9: Nombre y fecha del aprobador | L9: Solo después de aprobar se genera el código definitivo.
A10: 6 | B10: Activación | C10: Crear el registro maestro y habilitarlo para uso. | D10: Todos | E10: Administrador del sistema | F10: Socio administrador | G10: Completar campos obligatorios y estado Activo. | H10: Registro activo | I10: Activo | J10: 1 día | K10: Fecha de activación | L10: El código queda bloqueado para edición.
A11: 7 | B11: Comunicación | C11: Informar al equipo y actualizar manuales o listas. | D11: Todos | E11: Administración | G11: Confirmar que el nuevo registro sea visible en el sistema. | H11: Equipo informado | I11: Activo | J11: 1 día | K11: Notificación interna | L11: Usar el nuevo código solo desde la fecha de activación.
A12: 8 | B12: Seguimiento | C12: Verificar uso correcto durante el primer mes. | D12: Todos | E12: Administración / desarrollador | G12: Revisar movimientos, expedientes y reportes. | H12: Validación de implementación | I12: Activo | J12: 30 días | K12: Resultado de revisión | L12: Corregir descripciones, no códigos.
A13: 9 | B13: Inactivación | C13: Deshabilitar registros que ya no deban utilizarse. | D13: Categoría / Subcategoría / Servicio | E13: Administrador del catálogo | F13: Socio administrador | G13: Confirmar que no se eliminará histórico. | H13: Registro inactivo | I13: Inactivo | J13: Según necesidad | K13: Motivo y fecha | L13: Nunca borrar ni reutilizar el código.
A16: Situación | B16: Crear categoría | C16: Crear subcategoría | D16: Crear servicio | E16: Crear modalidad/tarifa | F16: Crear etiqueta | G16: Regla
A17: Nueva práctica jurídica independiente | B17: Sí | G17: Debe requerir medición separada en ingresos, utilidad y dashboard.
A18: División técnica dentro de una práctica | C18: Sí | G18: Debe agrupar varios servicios relacionados.
A19: Prestación concreta que se cotiza | D19: Sí | G19: Debe tener alcance, tarifa y resultado identificable.
A20: Mismo servicio con precio o forma de pago distinta | E20: Sí | G20: No crear código nuevo de servicio.
A21: Palabra alternativa de búsqueda | F21: Sí | G21: Usar etiquetas para búsquedas transversales.
A22: Servicio complementario | G22: Relacionarlo como servicio asociado; no duplicarlo.
A25: Regla ID | B25: Regla obligatoria | C25: Se puede modificar | D25: No se puede modificar | E25: Acción si está mal clasificado | F25: Responsable
A26: GOB-001 | B26: Los códigos son permanentes y no reutilizables. | C26: Nombre, descripción, etiquetas, tarifa, responsable y estado. | D26: Código, secuencia e histórico. | E26: Inactivar y crear un nuevo código. | F26: Administrador del catálogo
A27: GOB-002 | B27: No se elimina un registro con movimientos o expedientes. | C27: Estado y descripción. | D27: Registro histórico. | E27: Marcar Inactivo. | F27: Socio administrador
A28: GOB-003 | B28: Toda alta requiere revisión de duplicidad. | C28: Campos de la solicitud. | D28: Omisión del control. | E28: Rechazar y devolver la solicitud. | F28: Administrador del catálogo
A29: GOB-004 | B29: El sistema genera la secuencia del servicio. | C29: Datos descriptivos. | D29: Número secuencial manual. | E29: Solicitar código al sistema. | F29: Desarrollador / sistema
A30: GOB-005 | B30: Subcategorías deben ser únicas globalmente cuando sea posible. | C30: Nombre descriptivo antes de activar. | D30: Código una vez activo. | E30: Elegir otro código disponible. | F30: Administrador del catálogo
A33: Acción | B33: Socio administrador | C33: Administrador del catálogo | D33: Abogado / administración | E33: Desarrollador | F33: Regla
A34: Proponer categoría | B34: Sí | C34: Sí | D34: Sí | E34: No | F34: Cualquier propuesta debe justificarse.
A35: Aprobar categoría | B35: Sí | C35: No | D35: No | E35: No | F35: Aprobación exclusiva del socio administrador.
A36: Proponer subcategoría | B36: Sí | C36: Sí | D36: Sí | E36: No | F36: Debe pertenecer a una categoría activa.
A37: Aprobar subcategoría | B37: Sí | C37: No | D37: No | E37: No | F37: Aprobación exclusiva del socio administrador.
A38: Proponer servicio | B38: Sí | C38: Sí | D38: Sí | E38: No | F38: Debe incluir tarifa y alcance preliminar.
... A41: Modificar código | B41: No | C41: No | D41: No | E41: No | F41: Los códigos activos son inmutables.

Sheet 19_Control_Altas_Cambios
A1: 19 | Control de altas y cambios del catálogo
A2: Formato de trazabilidad. Temporalmente puede llenarse en Excel; posteriormente debe convertirse en un flujo de aprobación dentro del sistema.
A4: ID solicitud | B4: Fecha solicitud | C4: Tipo de solicitud | D4: Tipo de registro | E4: Nombre propuesto | F4: Categoría padre | G4: Subcategoría padre | H4: Código propuesto | I4: Código definitivo | J4: Descripción / alcance | K4: Motivo de la solicitud | L4: Etiquetas | M4: Solicitante | N4: Resultado revisión duplicidad | O4: Aprobador | P4: Fecha aprobación | Q4: Estado | R4: Observaciones
A5: SOL-2026-001 | B5: 46219 | C5: Alta | D5: Subcategoría | E5: Desarrollo y uso de suelo | F5: RAI | H5: DSU | J5: Servicios legales para parcelaciones, uso de suelo y desarrollo inmobiliario. | K5: Nueva línea de servicios inmobiliarios. | L5: desarrollo,uso de suelo,parcelación | M5: Andrea Escobar | N5: Sin duplicidad identificada | Q5: Solicitado | R5: Ejemplo de solicitud.

Sheet 20_Guia_Usuario
A1: 20 | Guía de usuario del archivo maestro AG Legal
A2: Esta hoja explica qué contiene el archivo, qué puede editarse, cómo registrar operaciones y cómo mantener correctamente el catálogo.
A4: Color / formato | B4: Significado | C4: ¿Se puede modificar? | D4: Qué hacer | E4: Ejemplo | F4: Responsable | G4: Riesgo si se altera | H4: Regla
A5: Texto azul | B5: Dato de entrada manual o supuesto editable | C5: Sí | D5: Actualizar únicamente con información real, aprobada o presupuestada. | E5: Tarifa, casos reales, ingresos reales, costos directos | F5: Administración / usuario autorizado | G5: Puede distorsionar metas y resultados si se ingresa mal. | H5: Sí: en general, lo azul es lo que se puede modificar.
A6: Texto negro | B6: Fórmula, resultado automático o dato controlado | C6: No, salvo indicación expresa | D6: No sobrescribir; si el resultado parece incorrecto, revisar los datos azules de origen. | E6: Cumplimiento, utilidad, margen, código definitivo | F6: Sistema / desarrollador | G6: Se rompen cálculos o trazabilidad. | H6: No editar fórmulas.
A7: Texto verde | B7: Código o dato maestro de referencia | C7: No directamente | D7: Usar para búsqueda y selección. Los cambios se tramitan en Control de Altas y Cambios. | E7: Código de servicio, categoría, subcategoría | F7: Administrador del catálogo | G7: Duplicidad o pérdida de histórico. | H7: Nunca editar un código activo.
A8: Encabezado azul oscuro | B8: Título o encabezado de sección | C8: No | D8: Solo sirve para organizar la información. | E8: Nombre de columnas | F8: N/A | G8: Pérdida de claridad visual. | H8: No editar.
A9: Semáforo verde/amarillo/rojo | B9: Resultado de cumplimiento automático | C9: No | D9: Revisar metas y datos reales que originan el resultado. | E9: Cumplimiento de ingresos | F9: Sistema | G9: Interpretación incorrecta si se pinta manualmente. | H9: No cambiar manualmente.
A12: Paso | B12: Qué necesito hacer | C12: Hoja principal | D12: Campo clave | E12: Resultado | F12: Quién lo hace | G12: Qué no hacer | H12: Frecuencia
A13: 1 | B13: Consultar una categoría o servicio existente | C13: 01, 02 y 03 | D13: Código, nombre o etiqueta | E13: Clasificación correcta del servicio | F13: Todo usuario | G13: No crear códigos fuera del catálogo | H13: Cada operación
A14: 2 | B14: Crear o abrir un expediente en el sistema | C14: 03 y 13 | D14: Código servicio, cliente, origen y honorarios | E14: Expediente clasificado | F14: Abogado / administración | G14: No escoger una categoría manual distinta al código | H14: Cada cliente o asunto
A15: 3 | B15: Registrar un ingreso o egreso | C15: 04 y 16 | D15: Código cuenta y, cuando aplique, código servicio | E15: Movimiento financiero codificado | F15: Administración | G15: No registrar movimientos sin cuenta | H15: Cada movimiento
A16: 4 | B16: Actualizar la realidad mensual mientras se implementa el sistema | C16: 15 | D16: Casos reales, ingresos reales, costos directos y comisión | E16: Cumplimiento y utilidad actualizados | F16: Administración | G16: No escribir sobre fórmulas negras | H16: Semanal / mensual
A17: 5 | B17: Revisar metas y resultados | C17: 17 y 10 | D17: Meta, real, cumplimiento, utilidad y semáforo | E17: Decisión comercial y financiera | F17: Socios / administración | G17: No confundir cartera con efectivo cobrado | H17: Semanal / mensual
A18: 6 | B18: Solicitar una categoría, subcategoría o servicio nuevo | C18: 18 y 19 | D18: Solicitud, motivo, revisión de duplicidad | E18: Alta controlada y trazable | F18: Solicitante / administrador | G18: No inventar el código definitivo | H18: Cuando sea necesario
A19: 7 | B19: Calcular comisión de Andrea | C19: 12 | D19: Origen, tipo de negocio, utilidad directa cobrada | E19: Comisión devengada correcta | F19: Administración / socio | G19: No calcular sobre IVA, reembolsos o cartera no cobrada | H19: Mensual
A22: Hoja | B22: Para qué sirve | C22: Quién la usa | D22: ¿Editable? | E22: Campos editables principales | F22: Alimenta | G22: Importancia | H22: Observación
A23: 00_Inicio | B23: Índice y reglas generales | C23: Todos | D23: No | E23: Ninguno | F23: Navegación | G23: Alta | H23: Leer primero.
A24: 01_Categorias | B24: Catálogo de categorías jurídicas | C24: Todos | D24: Controlado | E24: Nombre/estado solo mediante procedimiento | F24: Servicios y dashboard | G24: Crítica | H24: Códigos permanentes.
A25: 02_Subcategorias | B25: Segundo nivel de clasificación | C25: Todos | D25: Controlado | E25: Nombre/estado solo mediante procedimiento | F25: Servicios | G25: Crítica | H25: No debe repetir el código de categoría.
A26: 03_Catalogo_Servicios | B26: Listado oficial de servicios y códigos | C26: Todos | D26: Parcial | E26: Tarifa, costo, horas y algunos datos descriptivos en azul | F26: Expedientes y rentabilidad | G26: Crítica | H26: No editar códigos verdes.
A27: 04_Plan_Cuentas | B27: Códigos oficiales para ingresos y egresos | C27: Administración / desarrollador | D27: Controlado | E27: Altas mediante procedimiento | F27: P&L, flujo y dashboard | G27: Crítica | H27: Todo movimiento requiere cuenta.
A28: 05_Cartera_Proyectos | B28: Trabajo contratado pendiente de cobro | C28: Administración | D28: Sí | E28: Estado, probabilidad, mes esperado y valores | F28: Proyección | G28: Alta | H28: No equivale a efectivo.
A29: 06_Personal | B29: Salarios y honorarios fijos | C29: Socios / administración | D29: Sí | E29: Montos y períodos azules | F29: Gastos fijos | G29: Alta | H29: Andrea: fijo + variable separado.
A30: 07_Gastos_Fijos | B30: Supuestos de costos mensuales | C30: Socios / administración | D30: Sí | E30: Montos y porcentajes azules | F30: Punto de equilibrio | G30: Crítica | H30: Revisar cuando cambien costos.
A31: 08_Presupuesto_Jul_Dic | B31: Proyección por familias de servicios | C31: Socios / comercial | D31: Sí | E31: Volúmenes y tickets azules | F31: Metas | G31: Crítica | H31: No se proyecta por persona.
A32: 10_Dashboard | B32: Vista ejecutiva | C32: Socios | D32: No | E32: Ninguno | F32: Decisiones | G32: Alta | H32: Debe alimentarse del sistema.
A33: 12_Reglas_Comision | B33: Reglas de comisión de Andrea | C33: Socios / administración | D33: Controlado | E33: Porcentajes solo con aprobación | F33: Comisiones | G33: Alta | H33: Solo utilidad directa cobrada.
... A46: Nuevo servicio penal no existente | B46: No aplica aún | C46: No inventar | D46: Solicitud de alta | E46: 19_Control_Altas_Cambios | F46: Código aprobado y trazable | G46: Crear AGL-PEN-XXX manualmente | H46: Seguir el procedimiento de la hoja 18.
A49: REGLA RÁPIDA: Azul = entrada editable; negro = cálculo o control; verde = código maestro. Sin embargo, un campo azul solo debe modificarse por el usuario responsable y con información válida.
A58: DIFERENCIA CLAVE: ID interno = identificador técnico generado por el sistema y normalmente oculto. Código visible = identificador que utiliza el equipo, como PEN, DEF o AGL-PEN-DEF-002.
A60: Elemento | B60: Lo genera | C60: Lo utiliza | D60: Ejemplo | E60: ¿Se modifica? | F60: Dónde aparece | G60: Propósito | H60: Regla
A61: ID interno | B61: Sistema | C61: Sistema / desarrollador | D61: service_id = 104 | E61: No | F61: Base de datos | G61: Relacionar tablas | H61: No lo ingresa el usuario.
A62: Código categoría | B62: Administrador aprobado | C62: Equipo y sistema | D62: PEN | E62: No después de activar | F62: Catálogo y filtros | G62: Identificar práctica | H62: Único y permanente.
A63: Código subcategoría | B63: Administrador aprobado | C63: Equipo y sistema | D63: DEF | E63: No después de activar | F63: Catálogo y filtros | G63: Identificar división técnica | H63: Único y permanente.
A64: Código servicio | B64: Sistema después de aprobación | C64: Equipo y sistema | D64: AGL-PEN-DEF-002 | E64: No | F64: Expedientes y movimientos | G64: Identificar prestación | H64: Nunca reutilizar.

Sheet 00_PARA_DESARROLLADOR
A1: 00 | PARA EL DESARROLLADOR — Especificación única de implementación
A2: Esta es la hoja principal que debe usar el desarrollador. Resume la arquitectura, campos, relaciones, códigos, cálculos, dashboard y reglas de gobierno.
A4: Concepto | B4: Qué es | C4: Quién lo genera | D4: Quién lo ve | E4: Ejemplo | F4: ¿Editable? | G4: Uso técnico | H4: Uso operativo | I4: Regla | J4: Tabla sugerida | K4: Campo sugerido | L4: Relación | M4: Prioridad | N4: Nota
A5: ID interno del sistema | B5: Identificador técnico automático de cada registro. | C5: Sistema | D5: Normalmente no el usuario | E5: 104 | F5: No | G5: Relacionar tablas y preservar histórico | H5: Ninguno directo | I5: Nunca reutilizar ni modificar | J5: servicios | K5: service_id | L5: Clave primaria | M5: Crítica | N5: Puede ser entero autoincremental o UUID.
A6: Código visible de categoría | B6: Código corto que identifica una práctica jurídica. | C6: Administrador aprobado | D6: Equipo | E6: PEN | F6: No después de activar | G6: Filtros y reportes | H6: Búsqueda y clasificación | I6: Único y permanente | J6: categorias | K6: category_code | L6: category_id | M6: Crítica | N6: Ejemplo: PEN = Derecho Penal.
A7: Código visible de subcategoría | B7: Código corto del segundo nivel de clasificación. | C7: Administrador aprobado | D7: Equipo | E7: DEF | F7: No después de activar | G7: Agrupar servicios | H7: Navegación | I7: Tres letras, distinto de su categoría | J7: subcategorias | K7: subcategory_code | L7: category_id | M7: Crítica | N7: Ejemplo: DEF = Defensa técnica penal.
A8: Código visible de servicio | B8: Código completo del servicio vendido. | C8: Sistema después de aprobación | D8: Equipo | E8: AGL-PEN-DEF-002 | F8: No | G8: Expedientes, cobros y rentabilidad | H8: Selección del servicio | I8: Formato AGL-CAT-SUB-000 | J8: servicios | K8: service_code | L8: subcategory_id | M8: Crítica | N8: El usuario selecciona código + nombre.
A9: Código de cuenta financiera | B9: Código que clasifica un ingreso o egreso. | C9: Administrador aprobado | D9: Administración | E9: ING-PEN-001 | F9: No después de activar | G9: P&L, flujo y dashboard | H9: Registro financiero | I9: Prefijo ING o EGR | J9: plan_cuentas | K9: account_code | L9: account_id | M9: Crítica | N9: Todo movimiento debe tener uno.
A12: Orden | B12: Tabla / módulo | C12: Finalidad | D12: Clave primaria interna | E12: Código visible | F12: Campo padre | G12: Campos mínimos | H12: Usuario ingresa | I12: Sistema completa | J12: Validaciones | K12: Dashboard | L12: Histórico | M12: Prioridad | N12: Ejemplo
A13: 1 | B13: categorias | C13: Líneas jurídicas principales | D13: category_id | E13: category_code | F13: — | G13: nombre, descripción, estado | H13: Nombre y descripción | I13: ID interno | J13: Código único | K13: Ingresos por categoría | L13: Sí | M13: Crítica | N13: PEN — Derecho Penal
A14: 2 | B14: subcategorias | C14: Divisiones técnicas | D14: subcategory_id | E14: subcategory_code | F14: category_id | G14: nombre, estado | H14: Categoría y nombre | I14: ID interno y código compuesto | J14: Código único global; diferente de categoría | K14: Ingresos por subcategoría | L14: Sí | M14: Crítica | N14: DEF — Defensa técnica penal
A15: 3 | B15: servicios | C15: Prestaciones comercializables | D15: service_id | E15: service_code | F15: subcategory_id | G15: nombre, etiquetas, tarifa, costo, estado | H15: Servicio y supuestos | I15: ID y código secuencial | J15: No duplicar prestación equivalente | K15: Frecuencia y rentabilidad | L15: Sí | M15: Crítica | N15: AGL-PEN-DEF-002
A16: 4 | B16: clientes | C16: Personas o empresas | D16: client_id | E16: client_code opcional | F16: — | G16: nombre, identificación, contacto, estado | H16: Datos del cliente | I16: ID interno | J16: Documento único cuando aplique | K16: Clientes nuevos/recurrentes | L16: Sí | M16: Alta | N16: CLI-0001
A17: 5 | B17: expedientes | C17: Asuntos o casos | D17: case_id | E17: case_code | F17: client_id + service_id | G17: origen, honorarios, estado, fechas | H17: Cliente, servicio, valores | I17: Categoría, subcategoría y códigos relacionados | J17: Servicio activo | K17: Pipeline y conversión | L17: Sí | M17: Crítica | N17: EXP-2026-0001
A18: 6 | B18: plan_cuentas | C18: Clasificación financiera | D18: account_id | E18: account_code | F18: — | G18: tipo, grupo, cuenta, estado | H18: Alta aprobada | I18: ID interno | J18: ING para ingreso; EGR para egreso | K18: P&L y flujo | L18: Sí | M18: Crítica | N18: EGR-LOC-001
A19: 7 | B19: movimientos | C19: Ingresos y egresos | D19: movement_id | E19: movement_code | F19: account_id; case_id opcional; service_id opcional | G19: fecha, tipo, monto, estado | H19: Datos de la transacción | I19: Cuenta, categoría y utilidad | J19: Código cuenta obligatorio | K19: Ingresos, costos y utilidad | L19: Sí | M19: Crítica | N19: MOV-2026-0001
A20: 8 | B20: forecast | C20: Metas por familia y mes | D20: forecast_id | E20: — | F20: familia + mes | G20: volumen, ticket, margen | H20: Metas autorizadas | I20: Ingreso proyectado | J20: Valores >= 0 | K20: Meta vs real | L20: Sí | M20: Alta | N20: 3 casos × $300
A21: 9 | B21: comisiones | C21: Variable de Andrea | D21: commission_id | E21: — | F21: movement_id + case_id | G21: origen, utilidad, porcentaje | H21: Validación de elegibilidad | I21: Comisión por tramos | J21: Solo sobre utilidad cobrada | K21: Comisión mensual | L21: Sí | M21: Crítica | N21: 10%-12%-15% / 5%
A24: Pantalla / flujo | B24: Qué selecciona el usuario | C24: Qué NO llena | D24: Qué completa el sistema | E24: Resultado | F24: Validación | G24: Fuente maestra | H24: Prioridad
A25: Nuevo expediente | B25: Cliente + servicio por código o nombre + honorarios + origen | C25: IDs internos, categoría y subcategoría | D25: IDs, categoría, subcategoría, tarifa de referencia y cuenta de ingreso sugerida | E25: Expediente correctamente clasificado | F25: Servicio activo | G25: 03_Catalogo_Servicios | H25: Crítica
A26: Registrar cobro | B26: Expediente + fecha + monto + impuestos/reembolsos | C26: Categoría, subcategoría y utilidad | D26: Código servicio, código cuenta, neto operativo, saldo y utilidad directa | E26: Ingreso real y dashboard actualizado | F26: No exceder saldo salvo ajuste | G26: 04_Plan_Cuentas | H26: Crítica
A27: Registrar egreso | B27: Código cuenta + proveedor + fecha + monto + expediente si aplica | C27: Categoría jurídica si no aplica | D27: Centro de costo y relación con servicio cuando existe | E27: Costo clasificado | F27: EGR obligatorio | G27: 04_Plan_Cuentas | H27: Crítica
A28: Alta de catálogo | B28: Nombre, alcance, motivo y nivel propuesto | C28: ID interno ni código definitivo | D28: Revisión de duplicidad, secuencia y código final | E28: Registro aprobado y trazable | F28: Aprobación previa | G28: 18 y 19 | H28: Crítica
A31: KPI | B31: Fórmula funcional | C31: Fuente | D31: Filtros | E31: Meta / semáforo | F31: Frecuencia | G31: Drill-down | H31: Incluye proyección | I31: Incluye realidad | J31: Incluye utilidad | K31: Incluye comisión | L31: Visual | M31: Prioridad | N31: Nota
A32: Ingresos cobrados | B32: SUM(monto_neto_operativo de ingresos cobrados) | C32: movimientos | D32: Mes, categoría, subcategoría, servicio, origen | E32: Meta mensual | F32: Automática | G32: Movimientos y expedientes | H32: No | I32: Sí | J32: Sí | K32: No | L32: Tarjeta + tendencia | M32: Crítica | N32: Excluir IVA y fondos de terceros.
A33: Ingresos proyectados | B33: SUM(volumen_meta*ticket_objetivo)+cartera ponderada | C33: forecast + expedientes | D33: Mes y familia | E33: Meta aprobada | F33: Automática | G33: Expedientes proyectados | H33: Sí | I33: No | J33: Sí | K33: No | L33: Columnas | M33: Crítica
A34: Cumplimiento ingresos | B34: Ingresos reales / meta | C34: movimientos + forecast | D34: Mes, familia | E34: Verde >=100%; amarillo 85%-99%; rojo <85% | F34: Automática | G34: Servicios del período | H34: Sí | I34: Sí | J34: Sí | K34: No | L34: Barra progreso | M34: Crítica
A35: Utilidad operativa | B35: Ingresos - costos directos - gastos fijos - comisión | C35: movimientos + gastos + comisiones | D35: Mes, categoría | E35: Mínimo 20% margen | F35: Automática | G35: P&L | H35: Sí | I35: Sí | J35: Sí | K35: Sí | L35: Tarjeta + tendencia | M35: Crítica
A36: Servicios frecuentes y rentables | B36: COUNT(casos), SUM(utilidad), margen | C36: expedientes + movimientos | D36: Mes, categoría, servicio | E36: Ranking | F36: Automática | G36: Código de servicio | H36: No | I36: Sí | J36: Sí | K36: No | L36: Matriz / barras | M36: Alta
A37: Comisión Andrea | B37: Reglas 10%-12%-15% o 5% | C37: comisiones | D37: Mes, cliente, expediente | E37: Solo cobrado y elegible | F37: Automática | G37: Detalle por negocio | H37: No | I37: Sí | J37: Sí | K37: Sí | L37: Tarjeta + tabla | M37: Crítica
A40: Hoja de este archivo | B40: Uso para el desarrollador | C40: Importar como maestro | D40: Usar como regla | E40: Usar como ejemplo | F40: Modificar | G40: Prioridad | H40: Comentario
A41: 01_Categorias | B41: Maestro de categorías | C41: Sí | F41: No | G41: Crítica
A42: 02_Subcategorias | B42: Maestro de subcategorías | C42: Sí | F42: No | G42: Crítica
A43: 03_Catalogo_Servicios | B43: Maestro de servicios | C43: Sí | F43: Solo campos autorizados | G43: Crítica
A44: 04_Plan_Cuentas | B44: Maestro de cuentas de ingresos y egresos | C44: Sí | F44: No | G44: Crítica
A45: 12_Reglas_Comision | B45: Lógica de compensación variable | D45: Sí | F45: No | G45: Crítica
A46: 13_Especificacion_Sistema | B46: Detalle ampliado de campos y validaciones | D46: Sí | F46: No | G46: Alta | H46: Anexo técnico.
A47: 14_Dashboard_KPIs | B47: Detalle ampliado de indicadores | D47: Sí | F47: No | G47: Alta | H47: Anexo de dashboard.
A48: 15_Cumplimiento_Metas | B48: Estructura temporal meta vs real | E48: Sí | F48: Sí, campos azules | G48: Alta | H48: Después se alimentará del sistema.
A49: 16_Movimientos_Codificados | B49: Ejemplo de estructura transaccional | E49: Sí | F49: Sí para pruebas | G49: Crítica
A50: 18_Procedimiento_Catalogo | B50: Gobierno y aprobación de cambios | D50: Sí | F50: No | G50: Crítica
A51: 19_Control_Altas_Cambios | B51: Ejemplo de workflow y auditoría | E51: Sí | F51: Sí | G51: Alta
A54: INSTRUCCIÓN CENTRAL: El desarrollador debe comenzar por esta hoja. Los ID internos los genera el sistema; el equipo de AG Legal trabaja con códigos visibles y nombres.
